Workbook
Name Circ: Complete!$I$13

Sheet Cover
B1: LBO MODEL | EXECUTIVE COVER
B2: Mohamed Magdy | FP&A Analyst
B4: Decision-ready overview of the transaction, operating case, returns and model controls
B6: PROFILE | F6: MODEL SCOPE | J6: CONNECT WITH ME
B7: Role | C7: FP&A Analyst | F7: Model type | G7: Leveraged Buyout | J7: Email | K7: =HYPERLINK("mailto:mohamedeones123@gmail.com","Email me") -> Email me
B8: Location | C8: Tanta, Egypt | F8: Core outputs | G8: IRR | MOIC | Leverage | J8: LinkedIn | K8: =HYPERLINK("https://linkedin.com/in/mohamed-magdy-finance","LinkedIn profile") -> LinkedIn profile
B9: Focus | C9: FP&A / Modeling | F9: Analysis mode | G9: Base + sensitivity | J9: GitHub | K9: =HYPERLINK("https://github.com/Mohamed-Magdy-Finance","GitHub profile") -> GitHub profile
B10: Model | C10: Basic LBO model | F10: Decision use | G10: Returns & leverage | J10: Workbook | K10: Basic LBO model
B12: TRANSACTION SNAPSHOT | F12: OPERATING CASE | J12: MODEL STATUS
B13: LTM EBITDA | C13: =Summary!B5 -> 100 | F13: Revenue Growth | G13: =Summary!E5 -> 0.1 | J13: Checks | K13: =IF(Complete!D30=0,"PASS","REVIEW") -> PASS
B14: Purchase EV | C14: =Summary!B7 -> 1000 | F14: EBITDA Margin | G14: =Summary!E6 -> 0.1 | J14: Base Case IRR | K14: =Complete!I127 -> 0
B15: Sponsor Equity | C15: =Summary!B8 -> 427 | F15: Exit Multiple | G15: =Summary!E8 -> 10 | J15: Base Case MOIC | K15: =Complete!I128 -> 0
J16: Exit Debt | K16: =ABS(Complete!I114) -> 0
B18: VALUE CREATION
B19: Value drivers: operating growth | deleveraging | entry / exit discipline
B23: NAVIGATION
B24: Summary | C24: =HYPERLINK("#'Summary'!A1","Open executive summary") -> Open executive summary | F24: Complete | G24: =HYPERLINK("#'Complete'!A1","Open full model") -> Open full model | J24: Empty | K24: =HYPERLINK("#'Empty'!A1","Open blank template") -> Open blank template

Sheet Empty
B2: Basic LBO Model
B3: Template Structure | enter assumptions in blue cells; formulas and outputs should remain protected
B5: Step 1. Model Assumptions
B7: Entry Valuation | F7: Transaction Assumptions
B8: LTM EBITDA | F8: Transaction Fees
B9: Entry Multiple | F9: Financing Fees
B10: Purchase Enterprise Value | F10: Financing Fees Amortization Period
F11: Cash to B/S
F13: Circularity Toggle | I13: 1
B15: Debt Assumptions | C15: x EBITDA | D15: $ Amount | E15: Rate | F15: Floor | G15: % Amort. | H15: % Fee | I15: $ Fee
B16: Revolver
B17: Term Loan B
B18: Senior Notes
B19: Total Debt
B21: Step 2. Sources & Uses Table
B23: Sources & Uses
B24: Sources | C24: x EBITDA | D24: $ Amount | F24: Uses | I24: $ Amount
B25: Revolver | F25: Purchase Enterprise Value
B26: Term Loan B | F26: Cash to B/S
B27: Senior Notes | F27: Transaction Fees
B28: Sponsor Equity | F28: Financing Fees
B29: Total Sources | F29: Total Uses
B31: Step 3. Free Cash Flow Projection
B33: FCF Projection | D33: 2020 | E33: =+D33+1 -> 2021 | F33: =+E33+1 -> 2022 | G33: =+F33+1 -> 2023 | H33: =+G33+1 -> 2024 | I33: =+H33+1 -> 2025
B34: ($ in millions)
B36: Revenue
B37: Operating Forecast
B38: EBITDA
B39: Less: D&A
B40: EBIT
B41: Less: Interest
B42: Less: Amortization of Financing Fees
B43: EBT
B44: Less: Taxes
B45: Net Income
B46: Plus: D&A
... B67: Step 4. Debt Schedule
B69: Debt Schedule | E69: 2021 | F69: =+E69+1 -> 2022 | G69: =+F69+1 -> 2023 | H69: =+G69+1 -> 2024 | I69: =+H69+1 -> 2025
B70: ($ in millions)
B72: LIBOR (%) | E72: 0.015 | F72: =+E72+0.2% -> 0.017 | G72: =+F72+0.2% -> 0.019 | H72: =+G72+0.2% -> 0.021 | I72: =+H72+0.2% -> 0.023
B74: Revolver
B75: Beginning Balance
B76: Revolver Drawdown / (Paydown)
B77: Ending Balance
B79: Total Revolver Capacity
B81: Beginning Available Capacity
B82: Ending Available Capacity
B84: Revolver Interest Rate
B85: Revolver Interest Expense
B87: Unused Revolver Commitment Fee
B88: Unused Commitment Fee
B89: Revolver Roll-Forward Check
... B107: Exit Valuation Build
B108: Exit Valuation | D108: 2020 | E108: =+D108+1 -> 2021 | F108: =+E108+1 -> 2022 | G108: =+F108+1 -> 2023 | H108: =+G108+1 -> 2024 | I108: =+H108+1 -> 2025
B109: ($ in millions)
B111: Exit LTM EBITDA
B112: Exit Multiple Assumption
B113: Exit Enterprise Value
B114: Less: Debt
B115: Plus: Cash
B116: Exit Equity Value
B117: Exit Equity Check
B118: Liquidity / Minimum Cash Check
B119: Cash (Outflows) / Inflows | D119: 0 | E119: =+D119+1 -> 1 | F119: =+E119+1 -> 2 | G119: =+F119+1 -> 3 | H119: =+G119+1 -> 4 | I119: =+H119+1 -> 5
D120: 44196 | E120: =+EOMONTH(D120,12) -> 44561 | F120: =+EOMONTH(E120,12) -> 44926 | G120: =+EOMONTH(F120,12) -> 45291 | H120: =+EOMONTH(G120,12) -> 45657 | I120: =+EOMONTH(H120,12) -> 46022
B121: 2021
B122: =+B121+1 -> 2022
B123: =+B122+1 -> 2023
B124: =+B123+1 -> 2024
B125: =+B124+1 -> 2025
B126: Returns Check
B127: IRR
B128: MOIC

Sheet Summary
A1: LBO MODEL | EXECUTIVE SUMMARY
A2: Decision Dashboard
A4: Transaction Overview | D4: Operating Case
A5: LTM EBITDA | B5: =Complete!D8 -> 100 | D5: Revenue Growth | E5: =Complete!D60 -> 0.1
A6: Entry Multiple | B6: =Complete!D9 -> 10 | D6: EBITDA Margin | E6: =Complete!D61 -> 0.1
A7: Purchase Enterprise Value | B7: =Complete!D10 -> 1000 | D7: Tax Rate | E7: =Complete!E65 -> 0.35
A8: Sponsor Equity | B8: =Complete!D28 -> 427 | D8: Exit Multiple | E8: =Complete!E112 -> 10
A9: Initial Leverage | B9: =Complete!C19 -> 6 | D9: Minimum Cash | E9: =MIN(Complete!E57:I57)+0 -> 0
A12: Returns by Exit Year
A13: Metric | B13: =+Complete!E108 -> 2021 | C13: =+Complete!F108 -> 2022 | D13: =+Complete!G108 -> 2023 | E13: =+Complete!H108 -> 2024 | F13: =+Complete!I108 -> 2025
A14: IRR | B14: =+Complete!E127+0 -> 0 | C14: =+Complete!F127+0 -> 0 | D14: =+Complete!G127+0 -> 0 | E14: =+Complete!H127+0 -> 0 | F14: =+Complete!I127+0 -> 0
A15: MOIC | B15: =+Complete!E128+0 -> 0 | C15: =+Complete!F128+0 -> 0 | D15: =+Complete!G128+0 -> 0 | E15: =+Complete!H128+0 -> 0 | F15: =+Complete!I128+0 -> 0
A17: Model Checks | D17: Decision Notes
A18: Sources & Uses Check | B18: =+Complete!D30+0 -> 0 | D18: Base case IRR | E18: =+Complete!I127+0 -> 0
A19: Cash Roll-Forward Check | B19: =MAX(Complete!E58:I58)-MIN(Complete!E58:I58)+0 -> 0 | D19: Base case MOIC | E19: =+Complete!I128+0 -> 0
A20: Liquidity Check | B20: =MIN(Complete!E118:I118)+0 -> 0 | D20: Exit Debt | E20: =ABS(Complete!I114) -> 0
A21: Exit Equity Check | B21: =MAX(Complete!E117:I117)-MIN(Complete!E117:I117)+0 -> 0 | D21: Exit Cash | E21: =+Complete!I115+0 -> 0

Sheet Complete
B2: Basic LBO Model
B3: ($ in millions)
B5: Step 1. Model Assumptions
B7: Entry Valuation | F7: Transaction Assumptions
B8: LTM EBITDA | D8: 100 | F8: Transaction Fees | I8: 10
B9: Entry Multiple | D9: 10 | F9: Financing Fees | I9: 0.02
B10: Purchase Enterprise Value | D10: =+D8*D9 -> 1000 | F10: Financing Fees Amortization Period | I10: 7
F11: Cash to B/S | I11: 5
F13: Circularity Toggle | I13: 1
B15: Debt Assumptions | C15: x EBITDA | D15: $ Amount | E15: Rate | F15: Floor | G15: % Amort. | H15: % Fee | I15: $ Fee
B16: Revolver | C16: 0 | D16: =+C16*$D$8 -> 0 | E16: 400 | F16: 0 | G16: 0 | H16: =+$I$9 -> 0.02 | I16: =+D16*H16 -> 0
B17: Term Loan B | C17: 4 | D17: =+C17*$D$8 -> 400 | E17: 400 | F17: 0.02 | G17: 0.05 | H17: =+$I$9 -> 0.02 | I17: =+D17*H17 -> 8
B18: Senior Notes | C18: 2 | D18: =+C18*$D$8 -> 200 | E18: 0.085 | F18: 0 | G18: 0 | H18: =+$I$9 -> 0.02 | I18: =+D18*H18 -> 4
B19: Total Debt | C19: =SUM(C16:C18) -> 6 | D19: =SUM(D16:D18) -> 600 | I19: =SUM(I16:I18) -> 12
B21: Step 2. Sources & Uses Table
B23: Sources & Uses
B24: Sources | C24: x EBITDA | D24: $ Amount | F24: Uses | I24: $ Amount
B25: Revolver | C25: =+D25/$D$8 -> 0 | D25: =+D16 -> 0 | F25: Purchase Enterprise Value | I25: =+D10 -> 1000
B26: Term Loan B | C26: =+D26/$D$8 -> 4 | D26: =+D17 -> 400 | F26: Cash to B/S | I26: =+I11 -> 5
B27: Senior Notes | C27: =+D27/$D$8 -> 2 | D27: =+D18 -> 200 | F27: Transaction Fees | I27: =+I8 -> 10
B28: Sponsor Equity | C28: =+D28/$D$8 -> 4.27 | D28: =+I29-SUM(D25:D27) -> 427 | F28: Financing Fees | I28: =+I19 -> 12
B29: Total Sources | D29: =SUM(D25:D28) -> 1027 | F29: Total Uses | I29: =SUM(I25:I28) -> 1027
B30: Sources & Uses Check | D30: =D29-I29 -> 0
B31: Step 3. Free Cash Flow Projection
B33: FCF Projection | D33: 2020 | E33: =+D33+1 -> 2021 | F33: =+E33+1 -> 2022 | G33: =+F33+1 -> 2023 | H33: =+G33+1 -> 2024 | I33: =+H33+1 -> 2025
B34: ($ in millions)
B36: Revenue | D36: 1000 | E36: =+D36*(1+E60) -> 1100 | F36: =+E36*(1+F60) -> 1210 | G36: =+F36*(1+G60) -> 1331 | H36: =+G36*(1+H60) -> 1464.1 | I36: =+H36*(1+I60) -> 1610.51
B37: Operating Forecast
B38: EBITDA | D38: =+D8 -> 100 | E38: =+E61*E$36 -> 110 | F38: =+F61*F36 -> 121 | G38: =+G61*G36 -> 133.1 | H38: =+H61*H36 -> 146.41 | I38: =+I61*I36 -> 161.051
B39: Less: D&A | E39: =-E62*E36 -> -22 | F39: =-F62*F36 -> -24.2 | G39: =-G62*G36 -> -26.62 | H39: =-H62*H36 -> -29.282 | I39: =-I62*I36 -> -32.2102
B40: EBIT | E40: =SUM(E38:E39) -> 88 | F40: =SUM(F38:F39) -> 96.8 | G40: =SUM(G38:G39) -> 106.48 | H40: =SUM(H38:H39) -> 117.128 | I40: =SUM(I38:I39) -> 128.8408
B41: Less: Interest | E41: =-SUM(E85,E88,E96,E104) -> -40.525 | F41: =-SUM(F85,F88,F96,F104) -> -39.325 | G41: =-SUM(G85,G88,G96,G104) -> -38.125 | H41: =-SUM(H85,H88,H96,H104) -> -37.255 | I41: =-SUM(I85,I88,I96,I104) -> -36.655
B42: Less: Amortization of Financing Fees | E42: =-$I$19/$I$10 -> -1.7142857 | F42: =-$I$19/$I$10 -> -1.7142857 | G42: =-$I$19/$I$10 -> -1.7142857 | H42: =-$I$19/$I$10 -> -1.7142857 | I42: =-$I$19/$I$10 -> -1.7142857
B43: EBT | E43: =+SUM(E40:E42) -> 45.760714 | F43: =+SUM(F40:F42) -> 55.760714 | G43: =+SUM(G40:G42) -> 66.640714 | H43: =+SUM(H40:H42) -> 78.158714 | I43: =+SUM(I40:I42) -> 90.471514
B44: Less: Taxes | E44: =-E65*E43 -> -16.01625 | F44: =-F65*F43 -> -19.51625 | G44: =-G65*G43 -> -23.32425 | H44: =-H65*H43 -> -27.35555 | I44: =-I65*I43 -> -31.66503
B45: Net Income | E45: =+SUM(E43:E44) -> 29.744464 | F45: =+SUM(F43:F44) -> 36.244464 | G45: =+SUM(G43:G44) -> 43.316464 | H45: =+SUM(H43:H44) -> 50.803164 | I45: =+SUM(I43:I44) -> 58.806484
B46: Plus: D&A | E46: =-E39 -> 22 | F46: =-F39 -> 24.2 | G46: =-G39 -> 26.62 | H46: =-H39 -> 29.282 | I46: =-I39 -> 32.2102
B47: Plus: Amortization of Financing Fees | E47: =-E42 -> 1.7142857 | F47: =-F42 -> 1.7142857 | G47: =-G42 -> 1.7142857 | H47: =-H42 -> 1.7142857 | I47: =-I42 -> 1.7142857
B48: Less: Capex | E48: =-E63*E$36 -> -22 | F48: =-F63*F$36 -> -24.2 | G48: =-G63*G$36 -> -26.62 | H48: =-H63*H$36 -> -29.282 | I48: =-I63*I$36 -> -32.2102
B49: Less: Δ in NWC | E49: =-E64*E$36 -> -11 | F49: =-F64*F$36 -> -12.1 | G49: =-G64*G$36 -> -13.31 | H49: =-H64*H$36 -> -14.641 | I49: =-I64*I$36 -> -16.1051
B50: Less: Mandatory Amortization | E50: =+E92 -> -20 | F50: =+F92 -> -20 | G50: =+G92 -> -20 | H50: =+H92 -> -20 | I50: =+I92 -> -20
B51: Free Cash Flow (Pre-Revolver) | E51: =SUM(E45:E50) -> 0.45875 | F51: =SUM(F45:F50) -> 5.85875 | G51: =SUM(G45:G50) -> 11.72075 | H51: =SUM(H45:H50) -> 17.87645 | I51: =SUM(I45:I50) -> 24.41567
B52: Revolver Drawdown / (Paydown) | E52: =E76 -> 0 | F52: =F76 -> 0 | G52: =G76 -> 0 | H52: =H76 -> 0 | I52: =I76 -> 0
B53: Free Cash Flow (Post-Revolver) | E53: =SUM(E51:E52) -> 0.45875 | F53: =SUM(F51:F52) -> 5.85875 | G53: =SUM(G51:G52) -> 11.72075 | H53: =SUM(H51:H52) -> 17.87645 | I53: =SUM(I51:I52) -> 24.41567
B54: Cash Flow Bridge
B55: Beginning Cash Balance | E55: =+I11 -> 5 | F55: =+E57 -> 5.45875 | G55: =+F57 -> 11.3175 | H55: =+G57 -> 23.03825 | I55: =+H57 -> 40.9147
B56: Net Change in Cash Flow | E56: =+E53 -> 0.45875 | F56: =+F53 -> 5.85875 | G56: =+G53 -> 11.72075 | H56: =+H53 -> 17.87645 | I56: =+I53 -> 24.41567
B57: Ending Cash Balance | E57: =SUM(E55:E56) -> 5.45875 | F57: =SUM(F55:F56) -> 11.3175 | G57: =SUM(G55:G56) -> 23.03825 | H57: =SUM(H55:H56) -> 40.9147 | I57: =SUM(I55:I56) -> 65.33037
B58: Cash Roll-Forward Check | E58: =E55+E56-E57 -> 0 | F58: =F55+F56-F57 -> 0 | G58: =G55+G56-G57 -> 0 | H58: =H55+H56-H57 -> 0 | I58: =I55+I56-I57 -> 0
B59: Operating Assumptions
B60: Revenue Growth % | D60: 0.1 | E60: =+D60 -> 0.1 | F60: =+E60 -> 0.1 | G60: =+F60 -> 0.1 | H60: =+G60 -> 0.1 | I60: =+H60 -> 0.1
B61: EBITDA Margin % | D61: =+D38/D36 -> 0.1 | E61: =+D61 -> 0.1 | F61: =+E61 -> 0.1 | G61: =+F61 -> 0.1 | H61: =+G61 -> 0.1 | I61: =+H61 -> 0.1
B62: D&A % of Revenue | E62: 0.02 | F62: =+E62 -> 0.02 | G62: =+F62 -> 0.02 | H62: =+G62 -> 0.02 | I62: =+H62 -> 0.02
B63: Capex % of Revenue | E63: 0.02 | F63: =+E63 -> 0.02 | G63: =+F63 -> 0.02 | H63: =+G63 -> 0.02 | I63: =+H63 -> 0.02
B64: Δ in NWC % of Revenue | E64: 0.01 | F64: =+E64 -> 0.01 | G64: =+F64 -> 0.01 | H64: =+G64 -> 0.01 | I64: =+H64 -> 0.01
B65: Tax Rate % | E65: 0.35 | F65: =+E65 -> 0.35 | G65: =+F65 -> 0.35 | H65: =+G65 -> 0.35 | I65: =+H65 -> 0.35
B67: Step 4. Debt Schedule
B69: Debt Schedule | E69: 2021 | F69: =+E69+1 -> 2022 | G69: =+F69+1 -> 2023 | H69: =+G69+1 -> 2024 | I69: =+H69+1 -> 2025
B70: ($ in millions)
B72: LIBOR (%) | E72: 0.015 | F72: =+E72+0.2% -> 0.017 | G72: =+F72+0.2% -> 0.019 | H72: =+G72+0.2% -> 0.021 | I72: =+H72+0.2% -> 0.023
B74: Revolver
B75: Beginning Balance | E75: =+D25 -> 0 | F75: =+E77 -> 0 | G75: =+F77 -> 0 | H75: =+G77 -> 0 | I75: =+H77 -> 0
B76: Revolver Drawdown / (Paydown) | E76: =MIN(E81,-MIN(E75,E51)) -> 0 | F76: =MIN(F81,-MIN(F75,F51)) -> 0 | G76: =MIN(G81,-MIN(G75,G51)) -> 0 | H76: =MIN(H81,-MIN(H75,H51)) -> 0 | I76: =MIN(I81,-MIN(I75,I51)) -> 0
B77: Ending Balance | E77: =SUM(E75:E76) -> 0 | F77: =SUM(F75:F76) -> 0 | G77: =SUM(G75:G76) -> 0 | H77: =SUM(H75:H76) -> 0 | I77: =SUM(I75:I76) -> 0
B79: Total Revolver Capacity | E79: 50 | F79: =+E79 -> 50 | G79: =+F79 -> 50 | H79: =+G79 -> 50 | I79: =+H79 -> 50
B81: Beginning Available Capacity | E81: =+E79-E75 -> 50 | F81: =+F79-F75 -> 50 | G81: =+G79-G75 -> 50 | H81: =+H79-H75 -> 50 | I81: =+I79-I75 -> 50
B82: Ending Available Capacity | E82: =+E81-E76 -> 50 | F82: =+F81-F76 -> 50 | G82: =+G81-G76 -> 50 | H82: =+H81-H76 -> 50 | I82: =+I81-I76 -> 50
B84: Revolver Interest Rate | E84: =MAX($F$16,E$72)+($E$16/10000) -> 0.055 | F84: =MAX($F$16,F$72)+($E$16/10000) -> 0.057 | G84: =MAX($F$16,G$72)+($E$16/10000) -> 0.059 | H84: =MAX($F$16,H$72)+($E$16/10000) -> 0.061 | I84: =MAX($F$16,I$72)+($E$16/10000) -> 0.063
B85: Revolver Interest Expense | E85: =IF(Circ=1,AVERAGE(E75,E77),0)*E84 -> 0 | F85: =IF(Circ=1,AVERAGE(F75,F77),0)*F84 -> 0 | G85: =IF(Circ=1,AVERAGE(G75,G77),0)*G84 -> 0 | H85: =IF(Circ=1,AVERAGE(H75,H77),0)*H84 -> 0 | I85: =IF(Circ=1,AVERAGE(I75,I77),0)*I84 -> 0
B87: Unused Revolver Commitment Fee | E87: 0.0025 | F87: =+E87 -> 0.0025 | G87: =+F87 -> 0.0025 | H87: =+G87 -> 0.0025 | I87: =+H87 -> 0.0025
B88: Unused Commitment Fee | E88: =+IF($I$13=1,AVERAGE(E81,E82),0)*E87 -> 0.125 | F88: =+IF($I$13=1,AVERAGE(F81,F82),0)*F87 -> 0.125 | G88: =+IF($I$13=1,AVERAGE(G81,G82),0)*G87 -> 0.125 | H88: =+IF($I$13=1,AVERAGE(H81,H82),0)*H87 -> 0.125 | I88: =+IF($I$13=1,AVERAGE(I81,I82),0)*I87 -> 0.125
B89: Revolver Roll-Forward Check | E89: =E75+E76-E77 -> 0 | F89: =F75+F76-F77 -> 0 | G89: =G75+G76-G77 -> 0 | H89: =H75+H76-H77 -> 0 | I89: =I75+I76-I77 -> 0
B90: Term Loan B
B91: Beginning Balance | E91: =+D26 -> 400 | F91: =+E93 -> 380 | G91: =+F93 -> 360 | H91: =+G93 -> 340 | I91: =+H93 -> 320
B92: Less: Mandatory Amortization | E92: =-MIN($G$17*$D$26,E91) -> -20 | F92: =-MIN($G$17*$D$26,F91) -> -20 | G92: =-MIN($G$17*$D$26,G91) -> -20 | H92: =-MIN($G$17*$D$26,H91) -> -20 | I92: =-MIN($G$17*$D$26,I91) -> -20
B93: Ending Balance | E93: =SUM(E91:E92) -> 380 | F93: =SUM(F91:F92) -> 360 | G93: =SUM(G91:G92) -> 340 | H93: =SUM(H91:H92) -> 320 | I93: =SUM(I91:I92) -> 300
B95: TLB Interest Rate | E95: =MAX($F$17,E$72)+($E$17/10000) -> 0.06 | F95: =MAX($F$17,F$72)+($E$17/10000) -> 0.06 | G95: =MAX($F$17,G$72)+($E$17/10000) -> 0.06 | H95: =MAX($F$17,H$72)+($E$17/10000) -> 0.061 | I95: =MAX($F$17,I$72)+($E$17/10000) -> 0.063
B96: TLB Interest Expense | E96: =IF(Circ=1,AVERAGE(E91,E93),0)*E95 -> 23.4 | F96: =IF(Circ=1,AVERAGE(F91,F93),0)*F95 -> 22.2 | G96: =IF(Circ=1,AVERAGE(G91,G93),0)*G95 -> 21 | H96: =IF(Circ=1,AVERAGE(H91,H93),0)*H95 -> 20.13 | I96: =IF(Circ=1,AVERAGE(I91,I93),0)*I95 -> 19.53
B97: Term Loan Roll-Forward Check | E97: =E91+E92-E93 -> 0 | F97: =F91+F92-F93 -> 0 | G97: =G91+G92-G93 -> 0 | H97: =H91+H92-H93 -> 0 | I97: =I91+I92-I93 -> 0
B98: Senior Notes
B99: Beginning Balance | E99: =+D27 -> 200 | F99: =+E101 -> 200 | G99: =+F101 -> 200 | H99: =+G101 -> 200 | I99: =+H101 -> 200
B100: Less: Mandatory Amortization | E100: =+$D$27*$G$18 -> 0 | F100: =+$D$27*$G$18 -> 0 | G100: =+$D$27*$G$18 -> 0 | H100: =+$D$27*$G$18 -> 0 | I100: =+$D$27*$G$18 -> 0
B101: Ending Balance | E101: =SUM(E99:E100) -> 200 | F101: =SUM(F99:F100) -> 200 | G101: =SUM(G99:G100) -> 200 | H101: =SUM(H99:H100) -> 200 | I101: =SUM(I99:I100) -> 200
B103: Senior Notes Interest Rate | E103: =+$E$18 -> 0.085 | F103: =+$E$18 -> 0.085 | G103: =+$E$18 -> 0.085 | H103: =+$E$18 -> 0.085 | I103: =+$E$18 -> 0.085
B104: Senior Notes Interest Expense | E104: =+IF(Circ=1,AVERAGE(E99,E101),0)*E103 -> 17 | F104: =+IF(Circ=1,AVERAGE(F99,F101),0)*F103 -> 17 | G104: =+IF(Circ=1,AVERAGE(G99,G101),0)*G103 -> 17 | H104: =+IF(Circ=1,AVERAGE(H99,H101),0)*H103 -> 17 | I104: =+IF(Circ=1,AVERAGE(I99,I101),0)*I103 -> 17
B105: Senior Notes Roll-Forward Check | E105: =E99+E100-E101 -> 0 | F105: =F99+F100-F101 -> 0 | G105: =G99+G100-G101 -> 0 | H105: =H99+H100-H101 -> 0 | I105: =I99+I100-I101 -> 0
B106: Step 5. Returns Calculation
B107: Exit Valuation Build
B108: Exit Valuation | D108: 2020 | E108: =+D108+1 -> 2021 | F108: =+E108+1 -> 2022 | G108: =+F108+1 -> 2023 | H108: =+G108+1 -> 2024 | I108: =+H108+1 -> 2025
B109: ($ in millions)
B111: Exit LTM EBITDA | E111: =+E38 -> 110 | F111: =+F38 -> 121 | G111: =+G38 -> 133.1 | H111: =+H38 -> 146.41 | I111: =+I38 -> 161.051
B112: Exit Multiple Assumption | E112: 10 | F112: =+E112 -> 10 | G112: =+F112 -> 10 | H112: =+G112 -> 10 | I112: =+H112 -> 10
B113: Exit Enterprise Value | E113: =+E111*E112 -> 1100 | F113: =+F111*F112 -> 1210 | G113: =+G111*G112 -> 1331 | H113: =+H111*H112 -> 1464.1 | I113: =+I111*I112 -> 1610.51
B114: Less: Debt | E114: =-SUM(E77,E93,E101) -> -580 | F114: =-SUM(F77,F93,F101) -> -560 | G114: =-SUM(G77,G93,G101) -> -540 | H114: =-SUM(H77,H93,H101) -> -520 | I114: =-SUM(I77,I93,I101) -> -500
B115: Plus: Cash | E115: =+E57 -> 5.45875 | F115: =+F57 -> 11.3175 | G115: =+G57 -> 23.03825 | H115: =+H57 -> 40.9147 | I115: =+I57 -> 65.33037
B116: Exit Equity Value | E116: =SUM(E113:E115) -> 525.45875 | F116: =SUM(F113:F115) -> 661.3175 | G116: =SUM(G113:G115) -> 814.03825 | H116: =SUM(H113:H115) -> 985.0147 | I116: =SUM(I113:I115) -> 1175.8404
B117: Exit Equity Check | E117: =E113+E114+E115-E116 -> 0 | F117: =F113+F114+F115-F116 -> 0 | G117: =G113+G114+G115-G116 -> 0 | H117: =H113+H114+H115-H116 -> 0 | I117: =I113+I114+I115-I116 -> 0
B118: Liquidity / Minimum Cash Check | E118: =MIN(E57,0) -> 0 | F118: =MIN(F57,0) -> 0 | G118: =MIN(G57,0) -> 0 | H118: =MIN(H57,0) -> 0 | I118: =MIN(I57,0) -> 0
B119: Cash (Outflows) / Inflows | D119: 0 | E119: =+D119+1 -> 1 | F119: =+E119+1 -> 2 | G119: =+F119+1 -> 3 | H119: =+G119+1 -> 4 | I119: =+H119+1 -> 5
D120: 44196 | E120: =+EOMONTH(D120,12) -> 44561 | F120: =+EOMONTH(E120,12) -> 44926 | G120: =+EOMONTH(F120,12) -> 45291 | H120: =+EOMONTH(G120,12) -> 45657 | I120: =+EOMONTH(H120,12) -> 46022
...

Sheet __tracelight_scratchpad__
