Workbook

Sheet Headcount Report
B2: Headcount Report
B3: Employee Name | C3: Annual Salary | D3: Department | E3: Hire Date
B4: Bryan Tublin | C4: 189000 | D4: Engineering | E4: 44927
B5: Adam Saraceno | C5: 150000 | D5: Engineering | E5: 44927
B6: Kristen Berman | C6: 160000 | D6: Engineering | E6: 44927
B7: Aaron E Berhanu | C7: 140000 | D7: Engineering | E7: 44927
B8: Tommy Leep | C8: 160000 | D8: Engineering | E8: 44927
B9: Nicholas Anderson | C9: 140000 | D9: Engineering | E9: 44927
B10: Jennie Tan | C10: 170000 | D10: Engineering | E10: 44927
B11: Bridget O'Brien | C11: 150000 | D11: Engineering | E11: 44927
B12: Jon D Fasoli | C12: 170000 | D12: Engineering | E12: 44927
B13: John Lee | C13: 200000 | D13: Executive | E13: 44927
B14: Amy Goldberg | C14: 180000 | D14: Executive | E14: 44927
B15: Chris Evans | C15: 185000 | D15: Executive | E15: 44927
... B35: David Bland | C35: 140000 | D35: Sales | E35: 46371
B37: Department Summary
B38: Engineering | C38: =COUNTIF($D$4:$D$35,B38) -> 12
B39: Sales | C39: =COUNTIF($D$4:$D$35,B39) -> 11
B40: Executive | C40: =COUNTIF($D$4:$D$35,B40) -> 3
B41: Finance | C41: =COUNTIF($D$4:$D$35,B41) -> 2
B42: Legal | C42: =COUNTIF($D$4:$D$35,B42) -> 2
B43: Implementation | C43: =COUNTIF($D$4:$D$35,B43) -> 2
B45: Total Employees | C45: =COUNTA(B4:B35) -> 32
B46: Total Annual Salary | C46: =SUM(C4:C35) -> 5034000
B47: Total Monthly Salary | C47: =C46/'Accounting Analysis'!$C$22 -> 419500

Sheet Bonus Accrual Schedule
B2: 1 - Accrual Table | D2: Accrual - At 100% attainment | K2: 2 - Actual Table | N2: 3 - Dec-26 Accrual
B3: Employee Name | C3: Annual Salary | D3: Bonus % | E3: Annual Bonus | F3: 46296 | G3: =EOMONTH(F3,1) -> 46356 | H3: =EOMONTH(G3,1) -> 46387 | I3: Q4-26 | K3: Attainment | L3: Q4-26 | N3: 45657
B4: John Lee | C4: 200000 | D4: 0.3 | E4: =C4*D4 -> 60000 | F4: =E4/12 -> 5000 | G4: =F4 -> 5000 | H4: =G4 -> 5000 | I4: =SUM(F4:H4) -> 15000 | K4: 0.92493725 | L4: =I4*K4 -> 13874.059 | N4: =L4-G4-F4 -> 3874.0588
B5: Amy Goldberg | C5: 180000 | D5: 0.3 | E5: =C5*D5 -> 54000 | F5: =E5/12 -> 4500 | G5: =F5 -> 4500 | H5: =G5 -> 4500 | I5: =SUM(F5:H5) -> 13500 | K5: 0.92493725 | L5: =I5*K5 -> 12486.653 | N5: =L5-G5-F5 -> 3486.6529
B6: Chris Evans | C6: 185000 | D6: 0.3 | E6: =C6*D6 -> 55500 | F6: =E6/12 -> 4625 | G6: =F6 -> 4625 | H6: =G6 -> 4625 | I6: =SUM(F6:H6) -> 13875 | K6: 0.92493725 | L6: =I6*K6 -> 12833.504 | N6: =L6-G6-F6 -> 3583.5043
B7: Bryan Tublin | C7: 189000 | D7: 0.2 | E7: =C7*D7 -> 37800 | F7: =E7/12 -> 3150 | G7: =F7 -> 3150 | H7: =G7 -> 3150 | I7: =SUM(F7:H7) -> 9450 | K7: 0.92493725 | L7: =I7*K7 -> 8740.657 | N7: =L7-G7-F7 -> 2440.657
B8: Adam Saraceno | C8: 150000 | D8: 0.2 | E8: =C8*D8 -> 30000 | F8: =E8/12 -> 2500 | G8: =F8 -> 2500 | H8: =G8 -> 2500 | I8: =SUM(F8:H8) -> 7500 | K8: 0.92493725 | L8: =I8*K8 -> 6937.0294 | N8: =L8-G8-F8 -> 1937.0294
B9: Kristen Berman | C9: 160000 | D9: 0.2 | E9: =C9*D9 -> 32000 | F9: =E9/12 -> 2666.6667 | G9: =F9 -> 2666.6667 | H9: =G9 -> 2666.6667 | I9: =SUM(F9:H9) -> 8000 | K9: 0.92493725 | L9: =I9*K9 -> 7399.498 | N9: =L9-G9-F9 -> 2066.1647
B10: Aaron E Berhanu | C10: 140000 | D10: 0.2 | E10: =C10*D10 -> 28000 | F10: =E10/12 -> 2333.3333 | G10: =F10 -> 2333.3333 | H10: =G10 -> 2333.3333 | I10: =SUM(F10:H10) -> 7000 | K10: 0.92493725 | L10: =I10*K10 -> 6474.5608 | N10: =L10-G10-F10 -> 1807.8941
B11: Tommy Leep | C11: 160000 | D11: 0.2 | E11: =C11*D11 -> 32000 | F11: =E11/12 -> 2666.6667 | G11: =F11 -> 2666.6667 | H11: =G11 -> 2666.6667 | I11: =SUM(F11:H11) -> 8000 | K11: 0.92493725 | L11: =I11*K11 -> 7399.498 | N11: =L11-G11-F11 -> 2066.1647
B12: Nicholas Anderson | C12: 140000 | D12: 0.2 | E12: =C12*D12 -> 28000 | F12: =E12/12 -> 2333.3333 | G12: =F12 -> 2333.3333 | H12: =G12 -> 2333.3333 | I12: =SUM(F12:H12) -> 7000 | K12: 0.92493725 | L12: =I12*K12 -> 6474.5608 | N12: =L12-G12-F12 -> 1807.8941
B13: Jennie Tan | C13: 170000 | D13: 0.2 | E13: =C13*D13 -> 34000 | F13: =E13/12 -> 2833.3333 | G13: =F13 -> 2833.3333 | H13: =G13 -> 2833.3333 | I13: =SUM(F13:H13) -> 8500 | K13: 0.92493725 | L13: =I13*K13 -> 7861.9666 | N13: =L13-G13-F13 -> 2195.3
B14: Bridget O'Brien | C14: 150000 | D14: 0.2 | E14: =C14*D14 -> 30000 | F14: =E14/12 -> 2500 | G14: =F14 -> 2500 | H14: =G14 -> 2500 | I14: =SUM(F14:H14) -> 7500 | K14: 0.92493725 | L14: =I14*K14 -> 6937.0294 | N14: =L14-G14-F14 -> 1937.0294
B15: Jon D Fasoli | C15: 170000 | D15: 0.2 | E15: =C15*D15 -> 34000 | F15: =E15/12 -> 2833.3333 | G15: =F15 -> 2833.3333 | H15: =G15 -> 2833.3333 | I15: =SUM(F15:H15) -> 8500 | K15: 0.92493725 | L15: =I15*K15 -> 7861.9666 | N15: =L15-G15-F15 -> 2195.3
... B35: David Bland | C35: 140000 | D35: 0.15 | E35: =C35*D35 -> 21000 | F35: =E35/12 -> 1750 | G35: =F35 -> 1750 | H35: =G35 -> 1750 | I35: =SUM(F35:H35) -> 5250 | K35: 0.92493725 | L35: =I35*K35 -> 4855.9206 | N35: =L35-G35-F35 -> 1355.9206
B37: Total | C37: =SUM(C4:C36) -> 5034000 | E37: =SUM(E4:E36) -> 966800 | F37: =SUM(F4:F36) -> 80566.667 | G37: =SUM(G4:G36) -> 80566.667 | H37: =SUM(H4:H36) -> 80566.667 | I37: =SUM(I4:I36) -> 241700 | L37: =SUM(L4:L36) -> 223557.33 | N37: =SUM(N4:N36) -> 62424
D41: Q4-26 Attainment
D42: Revenue was $9.2M compared to target $10M, which resulted in 92% attainment in bonus payout

Sheet Accounting Analysis
B2: Accounting Analysis
B3: Purpose: Find Accounting Errors
B4: Timing: Before period-close
B5: Audience: Controller, VP of Accounting
B7: Month over Month Analysis of Compensation
B8: Category | C8: 46327 | D8: =EOMONTH(C8,1) -> 46387 | E8: Change | F8: % Change | G8: Comments
B9: Salaries | C9: =SUMIFS('Headcount Report'!$C$4:$C$35,'Headcount Report'!$E$4:$E$35,"<="&EOMONTH(C8,0))/$C$22 -> 396166.67 | D9: =SUMIFS('Headcount Report'!$C$4:$C$35,'Headcount Report'!$E$4:$E$35,"<="&EOMONTH(D8,0))/$C$22 -> 419500 | E9: =D9-C9 -> 23333.333 | F9: =E9/C9 -> 0.05889777 | G9: Checked the headcount report and confirmed flux is due to hiring 2 employees in Dec-26
B10: Social Security/FICA | C10: =C9*$C$19 -> 25750.833 | D10: =D9*$C$19 -> 27267.5 | E10: =D10-C10 -> 1516.6667 | F10: =E10/C10 -> 0.05889777
B11: Medical Insurance | C11: =C9*$C$20 -> 31693.333 | D11: =D9*$C$20 -> 33560 | E11: =D11-C11 -> 1866.6667 | F11: =E11/C11 -> 0.05889777
B12: Commission | C12: =C9*$C$21 -> 39616.667 | D12: =D9*$C$21 -> 41950 | E12: =D12-C12 -> 2333.3333 | F12: =E12/C12 -> 0.05889777
B13: Bonus | C13: =SUM('Bonus Accrual Schedule'!G4:G35) -> 80566.667 | D13: =SUM('Bonus Accrual Schedule'!N4:N35) -> 62424 | E13: =D13-C13 -> -18142.667 | F13: =E13/C13 -> -0.22518825 | G13: Checked Dec-26 accrual and confirmed flux is a true-down of Q4-26 bonus accrual based on 92% attainment
B15: Total Compensation | C15: =SUM(C9:C13) -> 573794.17 | D15: =SUM(D9:D13) -> 584701.5 | E15: =SUM(E9:E13) -> 10907.333 | F15: =E15/C15 -> 0.019009139
B18: Assumptions & Rates
B19: FICA Rate | C19: 0.065
B20: Medical Insurance Rate | C20: 0.08
B21: Commission Rate | C21: 0.1
B22: Months in Year | C22: 12

Sheet Business Analysis
B2: Business Analysis
B3: Purpose: Provide business insights
B4: Timing: After period-close
B5: Audience: CEO, CFO, Board of Directors, Investors
B7: Month over Month Analysis of Compensation
B8: Category | C8: ='Accounting Analysis'!C8 -> 46327 | D8: ='Accounting Analysis'!D8 -> 46387 | E8: Change | F8: % Change | G8: Comments
B9: Salaries | C9: ='Accounting Analysis'!C9 -> 396166.67 | D9: ='Accounting Analysis'!D9 -> 419500 | E9: ='Accounting Analysis'!E9 -> 23333.333 | F9: ='Accounting Analysis'!F9 -> 0.05889777 | G9: We hired 2 new employees in Dec-26 in the Sales Dept as outlined in the budget
B10: Social Security/FICA | C10: ='Accounting Analysis'!C10 -> 25750.833 | D10: ='Accounting Analysis'!D10 -> 27267.5 | E10: ='Accounting Analysis'!E10 -> 1516.6667 | F10: ='Accounting Analysis'!F10 -> 0.05889777
B11: Medical Insurance | C11: ='Accounting Analysis'!C11 -> 31693.333 | D11: ='Accounting Analysis'!D11 -> 33560 | E11: ='Accounting Analysis'!E11 -> 1866.6667 | F11: ='Accounting Analysis'!F11 -> 0.05889777
B12: Commission | C12: ='Accounting Analysis'!C12 -> 39616.667 | D12: ='Accounting Analysis'!D12 -> 41950 | E12: ='Accounting Analysis'!E12 -> 2333.3333 | F12: ='Accounting Analysis'!F12 -> 0.05889777
B13: Bonus | C13: ='Accounting Analysis'!C13 -> 80566.667 | D13: ='Accounting Analysis'!D13 -> 62424 | E13: ='Accounting Analysis'!E13 -> -18142.667 | F13: ='Accounting Analysis'!F13 -> -0.22518825 | G13: Incentive bonus for Q4-26 was attained at 92% based on revenue target
B15: Total Compensation | C15: ='Accounting Analysis'!C15 -> 573794.17 | D15: ='Accounting Analysis'!D15 -> 584701.5 | E15: ='Accounting Analysis'!E15 -> 10907.333 | F15: ='Accounting Analysis'!F15 -> 0.019009139
B18: Assumptions & Rates
B19: FICA Rate | C19: ='Accounting Analysis'!C19 -> 0.065
B20: Medical Insurance Rate | C20: ='Accounting Analysis'!C20 -> 0.08
B21: Commission Rate | C21: ='Accounting Analysis'!C21 -> 0.1
B22: Months in Year | C22: ='Accounting Analysis'!C22 -> 12

Sheet __tracelight_scratchpad__
