Workbook

Sheet Cover
B2: MONTHLY BUDGET & FORECASTING TOOL
B3: Executive planning dashboard | Actuals, forecasts, and management reporting
B5: Prepared by Mohamed Magdy | mohamedeones123@gmail.com
B7: Revenue | D7: Gross Profit | F7: Operating Income | H7: Net Income
B8: ='Income Statement'!C6 -> 441690.11 | D8: ='Income Statement'!C8 -> 353352.09 | F8: ='Income Statement'!C16 -> 58656.097 | H8: ='Income Statement'!C22 -> 42335.735
B10: MODEL SNAPSHOT | E10: KEY ASSUMPTIONS | H10: QUICK LINKS
B11: Start date | C11: ='Actual Expenses'!C2 -> 46291 | E11: Tax rate | F11: ='Income Statement'!C40 -> 0.25 | H11: Actual Expenses | I11: =HYPERLINK("#'Actual Expenses'!A1","Open") -> Open
B12: Forecast end | C12: ='Income Statement'!N5 -> 46747 | E12: COGS % Rev. | F12: ='Income Statement'!C34 -> 0.2 | H12: Forecast | I12: =HYPERLINK("#Forecast!A1","Open") -> Open
B13: Forecast months | C13: =COLUMNS('Income Statement'!C5:N5) -> 12 | E13: Base price | F13: ='Income Statement'!C28 -> 250 | H13: Live Dynamic | I13: =HYPERLINK("#'Live Dynamic'!A1","Open") -> Open
H14: Income Stmt. | I14: =HYPERLINK("#'Income Statement'!A1","Open") -> Open
B15: ONLINE PROFILES
B16: LinkedIn | C16: =HYPERLINK("https://linkedin.com/in/mohamed-magdy-finance","LinkedIn") -> LinkedIn
B17: GitHub | C17: =HYPERLINK("https://github.com/Mohamed-Magdy-Finance","GitHub") -> GitHub
B20: Confidential | Internal planning use

Sheet Actual Expenses
B2: Start Date | C2: 46291
B4: Actual Operating Expenses
B5: Account # | C5: Department | D5: Description | E5: =C2 -> 46291 | F5: =EDATE(E5,1) -> 46321 | G5: =EDATE(F5,1) -> 46352 | H5: =EDATE(G5,1) -> 46382
B6: 11256 | C6: Marketing | D6: Paid Ads | E6: 22992 | F6: 24001 | G6: 26558 | H6: 25446
B7: 11257 | C7: Marketing | D7: Infuencers | E7: 53326 | F7: 54223 | G7: 51000 | H7: 50000
B8: 11259 | C8: Engineering | D8: Consulting | E8: 35888 | F8: 36880 | G8: 37995 | H8: 40000
B9: 11260 | C9: Engineering | D9: Travel | E9: 87942 | F9: 85224 | G9: 82469 | H9: 81005
B10: 11263 | C10: Support | D10: Software | E10: 92622 | F10: 90005 | G10: 87556 | H10: 84522
B11: 11264 | C11: Support | D11: Call Center | E11: 27416 | F11: 26554 | G11: 24330 | H11: 22338
B12: 11267 | C12: HR | D12: Recruiting Events | E12: 41696 | F12: 41696 | G12: 42558 | H12: 45448
B13: 11268 | C13: HR | D13: Meetups | E13: 60285 | F13: 61225 | G13: 68994 | H13: 72410

Sheet Forecast
B2: 1. Case | E2: Actuals | I2: Forecast
A3: x | B3: ='Actual Expenses'!B5 -> Account # | C3: ='Actual Expenses'!C5 -> Department | D3: ='Actual Expenses'!D5 -> Description | E3: ='Actual Expenses'!E5 -> 46291 | F3: ='Actual Expenses'!F5 -> 46321 | G3: ='Actual Expenses'!G5 -> 46352 | H3: ='Actual Expenses'!H5 -> 46382 | I3: =EDATE(H3,1) -> 46413 | J3: =EDATE(I3,1) -> 46444 | K3: =EDATE(J3,1) -> 46472 | L3: =EDATE(K3,1) -> 46503 | M3: =EDATE(L3,1) -> 46533 | N3: =EDATE(M3,1) -> 46564 | O3: =EDATE(N3,1) -> 46594 | P3: =EDATE(O3,1) -> 46625 | ... T3: =EDATE(S3,1) -> 46747
B4: ='Actual Expenses'!B6 -> 11256 | C4: ='Actual Expenses'!C6 -> Marketing | D4: ='Actual Expenses'!D6 -> Paid Ads | E4: ='Actual Expenses'!E6 -> 22992 | F4: ='Actual Expenses'!F6 -> 24001 | G4: ='Actual Expenses'!G6 -> 26558 | H4: ='Actual Expenses'!H6 -> 25446 | I4: =_xlfn.FORECAST.ETS(I$3,$E4:H4,$E$3:H$3) -> 26859.761 | J4: =_xlfn.FORECAST.ETS(J$3,$E4:I4,$E$3:I$3) -> 26922.594 | K4: =_xlfn.FORECAST.ETS(K$3,$E4:J4,$E$3:J$3) -> 28560.22 | L4: =_xlfn.FORECAST.ETS(L$3,$E4:K4,$E$3:K$3) -> 28501.432 | M4: =_xlfn.FORECAST.ETS(M$3,$E4:L4,$E$3:L$3) -> 30101.347 | N4: =_xlfn.FORECAST.ETS(N$3,$E4:M4,$E$3:M$3) -> 30111.719 | O4: =_xlfn.FORECAST.ETS(O$3,$E4:N4,$E$3:N$3) -> 31672.189 | P4: =_xlfn.FORECAST.ETS(P$3,$E4:O4,$E$3:O$3) -> 31683.439 | ... T4: =_xlfn.FORECAST.ETS(T$3,$E4:S4,$E$3:S$3) -> 34816.87
B5: ='Actual Expenses'!B7 -> 11257 | C5: ='Actual Expenses'!C7 -> Marketing | D5: ='Actual Expenses'!D7 -> Infuencers | E5: ='Actual Expenses'!E7 -> 53326 | F5: ='Actual Expenses'!F7 -> 54223 | G5: ='Actual Expenses'!G7 -> 51000 | H5: ='Actual Expenses'!H7 -> 50000 | I5: =_xlfn.FORECAST.ETS(I$3,$E5:H5,$E$3:H$3) -> 48858.544 | J5: =_xlfn.FORECAST.ETS(J$3,$E5:I5,$E$3:I$3) -> 47585.966 | K5: =_xlfn.FORECAST.ETS(K$3,$E5:J5,$E$3:J$3) -> 45844.021 | L5: =_xlfn.FORECAST.ETS(L$3,$E5:K5,$E$3:K$3) -> 44591.391 | M5: =_xlfn.FORECAST.ETS(M$3,$E5:L5,$E$3:L$3) -> 42871.655 | N5: =_xlfn.FORECAST.ETS(N$3,$E5:M5,$E$3:M$3) -> 41659.495 | O5: =_xlfn.FORECAST.ETS(O$3,$E5:N5,$E$3:N$3) -> 39701.198 | P5: =_xlfn.FORECAST.ETS(P$3,$E5:O5,$E$3:O$3) -> 38527.277 | ... T5: =_xlfn.FORECAST.ETS(T$3,$E5:S5,$E$3:S$3) -> 32319.266
B6: ='Actual Expenses'!B8 -> 11259 | C6: ='Actual Expenses'!C8 -> Engineering | D6: ='Actual Expenses'!D8 -> Consulting | E6: ='Actual Expenses'!E8 -> 35888 | F6: ='Actual Expenses'!F8 -> 36880 | G6: ='Actual Expenses'!G8 -> 37995 | H6: ='Actual Expenses'!H8 -> 40000 | I6: =_xlfn.FORECAST.ETS(I$3,$E6:H6,$E$3:H$3) -> 41183.971 | J6: =_xlfn.FORECAST.ETS(J$3,$E6:I6,$E$3:I$3) -> 42613.672 | K6: =_xlfn.FORECAST.ETS(K$3,$E6:J6,$E$3:J$3) -> 44036.168 | L6: =_xlfn.FORECAST.ETS(L$3,$E6:K6,$E$3:K$3) -> 45413.912 | M6: =_xlfn.FORECAST.ETS(M$3,$E6:L6,$E$3:L$3) -> 46814.567 | N6: =_xlfn.FORECAST.ETS(N$3,$E6:M6,$E$3:M$3) -> 48215.311 | O6: =_xlfn.FORECAST.ETS(O$3,$E6:N6,$E$3:N$3) -> 49616.148 | P6: =_xlfn.FORECAST.ETS(P$3,$E6:O6,$E$3:O$3) -> 51017.052 | ... T6: =_xlfn.FORECAST.ETS(T$3,$E6:S6,$E$3:S$3) -> 56620.877
B7: ='Actual Expenses'!B9 -> 11260 | C7: ='Actual Expenses'!C9 -> Engineering | D7: ='Actual Expenses'!D9 -> Travel | E7: ='Actual Expenses'!E9 -> 87942 | F7: ='Actual Expenses'!F9 -> 85224 | G7: ='Actual Expenses'!G9 -> 82469 | H7: ='Actual Expenses'!H9 -> 81005 | I7: =_xlfn.FORECAST.ETS(I$3,$E7:H7,$E$3:H$3) -> 78427.892 | J7: =_xlfn.FORECAST.ETS(J$3,$E7:I7,$E$3:I$3) -> 76178.043 | K7: =_xlfn.FORECAST.ETS(K$3,$E7:J7,$E$3:J$3) -> 73912.465 | L7: =_xlfn.FORECAST.ETS(L$3,$E7:K7,$E$3:K$3) -> 71611.91 | M7: =_xlfn.FORECAST.ETS(M$3,$E7:L7,$E$3:L$3) -> 69331.893 | N7: =_xlfn.FORECAST.ETS(N$3,$E7:M7,$E$3:M$3) -> 67050.575 | O7: =_xlfn.FORECAST.ETS(O$3,$E7:N7,$E$3:N$3) -> 64768.401 | P7: =_xlfn.FORECAST.ETS(P$3,$E7:O7,$E$3:O$3) -> 62480.729 | ... T7: =_xlfn.FORECAST.ETS(T$3,$E7:S7,$E$3:S$3) -> 53344.816
B8: ='Actual Expenses'!B10 -> 11263 | C8: ='Actual Expenses'!C10 -> Support | D8: ='Actual Expenses'!D10 -> Software | E8: ='Actual Expenses'!E10 -> 92622 | F8: ='Actual Expenses'!F10 -> 90005 | G8: ='Actual Expenses'!G10 -> 87556 | H8: ='Actual Expenses'!H10 -> 84522 | I8: =_xlfn.FORECAST.ETS(I$3,$E8:H8,$E$3:H$3) -> 81916.877 | J8: =_xlfn.FORECAST.ETS(J$3,$E8:I8,$E$3:I$3) -> 79206.408 | K8: =_xlfn.FORECAST.ETS(K$3,$E8:J8,$E$3:J$3) -> 76483.45 | L8: =_xlfn.FORECAST.ETS(L$3,$E8:K8,$E$3:K$3) -> 73792.488 | M8: =_xlfn.FORECAST.ETS(M$3,$E8:L8,$E$3:L$3) -> 71086.198 | N8: =_xlfn.FORECAST.ETS(N$3,$E8:M8,$E$3:M$3) -> 68267.761 | O8: =_xlfn.FORECAST.ETS(O$3,$E8:N8,$E$3:N$3) -> 65623.68 | P8: =_xlfn.FORECAST.ETS(P$3,$E8:O8,$E$3:O$3) -> 62955.109 | ... T8: =_xlfn.FORECAST.ETS(T$3,$E8:S8,$E$3:S$3) -> 51987.35
B9: ='Actual Expenses'!B11 -> 11264 | C9: ='Actual Expenses'!C11 -> Support | D9: ='Actual Expenses'!D11 -> Call Center | E9: ='Actual Expenses'!E11 -> 27416 | F9: ='Actual Expenses'!F11 -> 26554 | G9: ='Actual Expenses'!G11 -> 24330 | H9: ='Actual Expenses'!H11 -> 22338 | I9: =_xlfn.FORECAST.ETS(I$3,$E9:H9,$E$3:H$3) -> 20784.677 | J9: =_xlfn.FORECAST.ETS(J$3,$E9:I9,$E$3:I$3) -> 18966.367 | K9: =_xlfn.FORECAST.ETS(K$3,$E9:J9,$E$3:J$3) -> 17138.765 | L9: =_xlfn.FORECAST.ETS(L$3,$E9:K9,$E$3:K$3) -> 15398.473 | M9: =_xlfn.FORECAST.ETS(M$3,$E9:L9,$E$3:L$3) -> 13625.108 | N9: =_xlfn.FORECAST.ETS(N$3,$E9:M9,$E$3:M$3) -> 11459.691 | O9: =_xlfn.FORECAST.ETS(O$3,$E9:N9,$E$3:N$3) -> 10235.714 | P9: =_xlfn.FORECAST.ETS(P$3,$E9:O9,$E$3:O$3) -> 8271.2763 | ... T9: =_xlfn.FORECAST.ETS(T$3,$E9:S9,$E$3:S$3) -> 825.90662
B10: ='Actual Expenses'!B12 -> 11267 | C10: ='Actual Expenses'!C12 -> HR | D10: ='Actual Expenses'!D12 -> Recruiting Events | E10: ='Actual Expenses'!E12 -> 41696 | F10: ='Actual Expenses'!F12 -> 41696 | G10: ='Actual Expenses'!G12 -> 42558 | H10: ='Actual Expenses'!H12 -> 45448 | I10: =_xlfn.FORECAST.ETS(I$3,$E10:H10,$E$3:H$3) -> 46256.947 | J10: =_xlfn.FORECAST.ETS(J$3,$E10:I10,$E$3:I$3) -> 47704.638 | K10: =_xlfn.FORECAST.ETS(K$3,$E10:J10,$E$3:J$3) -> 49150.171 | L10: =_xlfn.FORECAST.ETS(L$3,$E10:K10,$E$3:K$3) -> 50452.329 | M10: =_xlfn.FORECAST.ETS(M$3,$E10:L10,$E$3:L$3) -> 51824.343 | N10: =_xlfn.FORECAST.ETS(N$3,$E10:M10,$E$3:M$3) -> 53196.599 | O10: =_xlfn.FORECAST.ETS(O$3,$E10:N10,$E$3:N$3) -> 54569.117 | P10: =_xlfn.FORECAST.ETS(P$3,$E10:O10,$E$3:O$3) -> 55941.82 | ... T10: =_xlfn.FORECAST.ETS(T$3,$E10:S10,$E$3:S$3) -> 61433.162
B11: ='Actual Expenses'!B13 -> 11268 | C11: ='Actual Expenses'!C13 -> HR | D11: ='Actual Expenses'!D13 -> Meetups | E11: ='Actual Expenses'!E13 -> 60285 | F11: ='Actual Expenses'!F13 -> 61225 | G11: ='Actual Expenses'!G13 -> 68994 | H11: ='Actual Expenses'!H13 -> 72410 | I11: =_xlfn.FORECAST.ETS(I$3,$E11:H11,$E$3:H$3) -> 76705.607 | J11: =_xlfn.FORECAST.ETS(J$3,$E11:I11,$E$3:I$3) -> 80731.326 | K11: =_xlfn.FORECAST.ETS(K$3,$E11:J11,$E$3:J$3) -> 87089.658 | L11: =_xlfn.FORECAST.ETS(L$3,$E11:K11,$E$3:K$3) -> 90875.73 | M11: =_xlfn.FORECAST.ETS(M$3,$E11:L11,$E$3:L$3) -> 96948.062 | N11: =_xlfn.FORECAST.ETS(N$3,$E11:M11,$E$3:M$3) -> 100800.22 | O11: =_xlfn.FORECAST.ETS(O$3,$E11:N11,$E$3:N$3) -> 106865.98 | P11: =_xlfn.FORECAST.ETS(P$3,$E11:O11,$E$3:O$3) -> 111036.03 | ... T11: =_xlfn.FORECAST.ETS(T$3,$E11:S11,$E$3:S$3) -> 131085.88
B13: Best | C13: 0.3
B15: 2. Base Case | E15: Actuals | I15: Forecast
A16: x | B16: =B3 -> Account # | C16: =C3 -> Department | D16: =D3 -> Description | E16: =E3 -> 46291 | F16: =F3 -> 46321 | G16: =G3 -> 46352 | H16: =H3 -> 46382 | I16: =EDATE(H16,1) -> 46413 | J16: =EDATE(I16,1) -> 46444 | K16: =EDATE(J16,1) -> 46472 | L16: =EDATE(K16,1) -> 46503 | M16: =EDATE(L16,1) -> 46533 | N16: =EDATE(M16,1) -> 46564 | O16: =EDATE(N16,1) -> 46594 | P16: =EDATE(O16,1) -> 46625 | ... T16: =EDATE(S16,1) -> 46747
B17: =B4 -> 11256 | C17: =C4 -> Marketing | D17: =D4 -> Paid Ads | E17: =E4 -> 22992 | F17: =F4 -> 24001 | G17: =G4 -> 26558 | H17: =H4 -> 25446 | I17: =I4*(1-$C$13) -> 18801.833 | J17: =J4*(1-$C$13) -> 18845.815 | K17: =K4*(1-$C$13) -> 19992.154 | L17: =L4*(1-$C$13) -> 19951.002 | M17: =M4*(1-$C$13) -> 21070.943 | N17: =N4*(1-$C$13) -> 21078.203 | O17: =O4*(1-$C$13) -> 22170.533 | P17: =P4*(1-$C$13) -> 22178.407 | ... T17: =T4*(1-$C$13) -> 24371.809
B18: =B5 -> 11257 | C18: =C5 -> Marketing | D18: =D5 -> Infuencers | E18: =E5 -> 53326 | F18: =F5 -> 54223 | G18: =G5 -> 51000 | H18: =H5 -> 50000 | I18: =I5*(1-$C$13) -> 34200.981 | J18: =J5*(1-$C$13) -> 33310.176 | K18: =K5*(1-$C$13) -> 32090.815 | L18: =L5*(1-$C$13) -> 31213.974 | M18: =M5*(1-$C$13) -> 30010.158 | N18: =N5*(1-$C$13) -> 29161.646 | O18: =O5*(1-$C$13) -> 27790.839 | P18: =P5*(1-$C$13) -> 26969.094 | ... T18: =T5*(1-$C$13) -> 22623.486
B19: =B6 -> 11259 | C19: =C6 -> Engineering | D19: =D6 -> Consulting | E19: =E6 -> 35888 | F19: =F6 -> 36880 | G19: =G6 -> 37995 | H19: =H6 -> 40000 | I19: =I6*(1-$C$13) -> 28828.78 | J19: =J6*(1-$C$13) -> 29829.57 | K19: =K6*(1-$C$13) -> 30825.318 | L19: =L6*(1-$C$13) -> 31789.738 | M19: =M6*(1-$C$13) -> 32770.197 | N19: =N6*(1-$C$13) -> 33750.718 | O19: =O6*(1-$C$13) -> 34731.303 | P19: =P6*(1-$C$13) -> 35711.936 | ... T19: =T6*(1-$C$13) -> 39634.614
B20: =B7 -> 11260 | C20: =C7 -> Engineering | D20: =D7 -> Travel | E20: =E7 -> 87942 | F20: =F7 -> 85224 | G20: =G7 -> 82469 | H20: =H7 -> 81005 | I20: =I7*(1-$C$13) -> 54899.524 | J20: =J7*(1-$C$13) -> 53324.63 | K20: =K7*(1-$C$13) -> 51738.726 | L20: =L7*(1-$C$13) -> 50128.337 | M20: =M7*(1-$C$13) -> 48532.325 | N20: =N7*(1-$C$13) -> 46935.402 | O20: =O7*(1-$C$13) -> 45337.88 | P20: =P7*(1-$C$13) -> 43736.51 | ... T20: =T7*(1-$C$13) -> 37341.371
B21: =B8 -> 11263 | C21: =C8 -> Support | D21: =D8 -> Software | E21: =E8 -> 92622 | F21: =F8 -> 90005 | G21: =G8 -> 87556 | H21: =H8 -> 84522 | I21: =I8*(1-$C$13) -> 57341.814 | J21: =J8*(1-$C$13) -> 55444.485 | K21: =K8*(1-$C$13) -> 53538.415 | L21: =L8*(1-$C$13) -> 51654.742 | M21: =M8*(1-$C$13) -> 49760.338 | N21: =N8*(1-$C$13) -> 47787.432 | O21: =O8*(1-$C$13) -> 45936.576 | P21: =P8*(1-$C$13) -> 44068.577 | ... T21: =T8*(1-$C$13) -> 36391.145
B22: =B9 -> 11264 | C22: =C9 -> Support | D22: =D9 -> Call Center | E22: =E9 -> 27416 | F22: =F9 -> 26554 | G22: =G9 -> 24330 | H22: =H9 -> 22338 | I22: =I9*(1-$C$13) -> 14549.274 | J22: =J9*(1-$C$13) -> 13276.457 | K22: =K9*(1-$C$13) -> 11997.136 | L22: =L9*(1-$C$13) -> 10778.931 | M22: =M9*(1-$C$13) -> 9537.5757 | N22: =N9*(1-$C$13) -> 8021.7835 | O22: =O9*(1-$C$13) -> 7164.9997 | P22: =P9*(1-$C$13) -> 5789.8934 | ... T22: =T9*(1-$C$13) -> 578.13463
B23: =B10 -> 11267 | C23: =C10 -> HR | D23: =D10 -> Recruiting Events | E23: =E10 -> 41696 | F23: =F10 -> 41696 | G23: =G10 -> 42558 | H23: =H10 -> 45448 | I23: =I10*(1-$C$13) -> 32379.863 | J23: =J10*(1-$C$13) -> 33393.247 | K23: =K10*(1-$C$13) -> 34405.12 | L23: =L10*(1-$C$13) -> 35316.63 | M23: =M10*(1-$C$13) -> 36277.04 | N23: =N10*(1-$C$13) -> 37237.62 | O23: =O10*(1-$C$13) -> 38198.382 | P23: =P10*(1-$C$13) -> 39159.274 | ... T23: =T10*(1-$C$13) -> 43003.214
B24: =B11 -> 11268 | C24: =C11 -> HR | D24: =D11 -> Meetups | E24: =E11 -> 60285 | F24: =F11 -> 61225 | G24: =G11 -> 68994 | H24: =H11 -> 72410 | I24: =I11*(1-$C$13) -> 53693.925 | J24: =J11*(1-$C$13) -> 56511.928 | K24: =K11*(1-$C$13) -> 60962.76 | L24: =L11*(1-$C$13) -> 63613.011 | M24: =M11*(1-$C$13) -> 67863.644 | N24: =N11*(1-$C$13) -> 70560.152 | O24: =O11*(1-$C$13) -> 74806.187 | P24: =P11*(1-$C$13) -> 77725.223 | ... T24: =T11*(1-$C$13) -> 91760.115
B26: Worst | C26: 0.2
B28: 3. Worst Case | E28: Actuals | I28: Forecast
B29: =B16 -> Account # | C29: =C16 -> Department | D29: =D16 -> Description | E29: =E16 -> 46291 | F29: =F16 -> 46321 | G29: =G16 -> 46352 | H29: =H16 -> 46382 | I29: =EDATE(H29,1) -> 46413 | J29: =EDATE(I29,1) -> 46444 | K29: =EDATE(J29,1) -> 46472 | L29: =EDATE(K29,1) -> 46503 | M29: =EDATE(L29,1) -> 46533 | N29: =EDATE(M29,1) -> 46564 | O29: =EDATE(N29,1) -> 46594 | P29: =EDATE(O29,1) -> 46625 | ... T29: =EDATE(S29,1) -> 46747
B30: =B17 -> 11256 | C30: =C17 -> Marketing | D30: =D17 -> Paid Ads | E30: =E17 -> 22992 | F30: =F17 -> 24001 | G30: =G17 -> 26558 | H30: =H17 -> 25446 | I30: =I4*(1+$C$26) -> 32231.713 | J30: =J4*(1+$C$26) -> 32307.112 | K30: =K4*(1+$C$26) -> 34272.264 | L30: =L4*(1+$C$26) -> 34201.718 | M30: =M4*(1+$C$26) -> 36121.616 | N30: =N4*(1+$C$26) -> 36134.063 | O30: =O4*(1+$C$26) -> 38006.627 | P30: =P4*(1+$C$26) -> 38020.127 | ... T30: =T4*(1+$C$26) -> 41780.245
B31: =B18 -> 11257 | C31: =C18 -> Marketing | D31: =D18 -> Infuencers | E31: =E18 -> 53326 | F31: =F18 -> 54223 | G31: =G18 -> 51000 | H31: =H18 -> 50000 | I31: =I5*(1+$C$26) -> 58630.252 | J31: =J5*(1+$C$26) -> 57103.16 | K31: =K5*(1+$C$26) -> 55012.825 | L31: =L5*(1+$C$26) -> 53509.669 | M31: =M5*(1+$C$26) -> 51445.985 | N31: =N5*(1+$C$26) -> 49991.393 | O31: =O5*(1+$C$26) -> 47641.438 | P31: =P5*(1+$C$26) -> 46232.733 | ... T31: =T5*(1+$C$26) -> 38783.119
B32: =B19 -> 11259 | C32: =C19 -> Engineering | D32: =D19 -> Consulting | E32: =E19 -> 35888 | F32: =F19 -> 36880 | G32: =G19 -> 37995 | H32: =H19 -> 40000 | I32: =I6*(1+$C$26) -> 49420.765 | J32: =J6*(1+$C$26) -> 51136.406 | K32: =K6*(1+$C$26) -> 52843.401 | L32: =L6*(1+$C$26) -> 54496.694 | M32: =M6*(1+$C$26) -> 56177.481 | N32: =N6*(1+$C$26) -> 57858.373 | O32: =O6*(1+$C$26) -> 59539.377 | P32: =P6*(1+$C$26) -> 61220.462 | ... T32: =T6*(1+$C$26) -> 67945.053
B33: =B20 -> 11260 | C33: =C20 -> Engineering | D33: =D20 -> Travel | E33: =E20 -> 87942 | F33: =F20 -> 85224 | G33: =G20 -> 82469 | H33: =H20 -> 81005 | I33: =I7*(1+$C$26) -> 94113.47 | J33: =J7*(1+$C$26) -> 91413.652 | K33: =K7*(1+$C$26) -> 88694.958 | L33: =L7*(1+$C$26) -> 85934.292 | M33: =M7*(1+$C$26) -> 83198.272 | N33: =N7*(1+$C$26) -> 80460.69 | O33: =O7*(1+$C$26) -> 77722.081 | P33: =P7*(1+$C$26) -> 74976.875 | ... T33: =T7*(1+$C$26) -> 64013.78
B34: =B21 -> 11263 | C34: =C21 -> Support | D34: =D21 -> Software | E34: =E21 -> 92622 | F34: =F21 -> 90005 | G34: =G21 -> 87556 | H34: =H21 -> 84522 | I34: =I8*(1+$C$26) -> 98300.252 | J34: =J8*(1+$C$26) -> 95047.689 | K34: =K8*(1+$C$26) -> 91780.14 | L34: =L8*(1+$C$26) -> 88550.986 | M34: =M8*(1+$C$26) -> 85303.437 | N34: =N8*(1+$C$26) -> 81921.313 | O34: =O8*(1+$C$26) -> 78748.416 | P34: =P8*(1+$C$26) -> 75546.131 | ... T34: =T8*(1+$C$26) -> 62384.82
B35: =B22 -> 11264 | C35: =C22 -> Support | D35: =D22 -> Call Center | E35: =E22 -> 27416 | F35: =F22 -> 26554 | G35: =G22 -> 24330 | H35: =H22 -> 22338 | I35: =I9*(1+$C$26) -> 24941.612 | J35: =J9*(1+$C$26) -> 22759.641 | K35: =K9*(1+$C$26) -> 20566.518 | L35: =L9*(1+$C$26) -> 18478.168 | M35: =M9*(1+$C$26) -> 16350.13 | N35: =N9*(1+$C$26) -> 13751.629 | O35: =O9*(1+$C$26) -> 12282.857 | P35: =P9*(1+$C$26) -> 9925.5316 | ... T35: =T9*(1+$C$26) -> 991.08794
B36: =B23 -> 11267 | C36: =C23 -> HR | D36: =D23 -> Recruiting Events | E36: =E23 -> 41696 | F36: =F23 -> 41696 | G36: =G23 -> 42558 | H36: =H23 -> 45448 | I36: =I10*(1+$C$26) -> 55508.336 | J36: =J10*(1+$C$26) -> 57245.566 | K36: =K10*(1+$C$26) -> 58980.206 | L36: =L10*(1+$C$26) -> 60542.794 | M36: =M10*(1+$C$26) -> 62189.211 | N36: =N10*(1+$C$26) -> 63835.919 | O36: =O10*(1+$C$26) -> 65482.94 | P36: =P10*(1+$C$26) -> 67130.184 | ... T36: =T10*(1+$C$26) -> 73719.795
A37: x | B37: =B24 -> 11268 | C37: =C24 -> HR | D37: =D24 -> Meetups | E37: =E24 -> 60285 | F37: =F24 -> 61225 | G37: =G24 -> 68994 | H37: =H24 -> 72410 | I37: =I11*(1+$C$26) -> 92046.728 | J37: =J11*(1+$C$26) -> 96877.591 | K37: =K11*(1+$C$26) -> 104507.59 | L37: =L11*(1+$C$26) -> 109050.88 | M37: =M11*(1+$C$26) -> 116337.67 | N37: =N11*(1+$C$26) -> 120960.26 | O37: =O11*(1+$C$26) -> 128239.18 | P37: =P11*(1+$C$26) -> 133243.24 | ... T37: =T11*(1+$C$26) -> 157303.05

Sheet Live Dynamic
D2: Operating Expenses Scenario
B4: 4. Live Case | E4: Actuals | I4: Forecast
A5: x | B5: ='Actual Expenses'!B5 -> Account # | C5: ='Actual Expenses'!C5 -> Department | D5: ='Actual Expenses'!D5 -> Description | E5: ='Actual Expenses'!E5 -> 46291 | F5: ='Actual Expenses'!F5 -> 46321 | G5: ='Actual Expenses'!G5 -> 46352 | H5: ='Actual Expenses'!H5 -> 46382 | I5: =EDATE(H5,1) -> 46413 | J5: =EDATE(I5,1) -> 46444 | K5: =EDATE(J5,1) -> 46472 | L5: =EDATE(K5,1) -> 46503 | M5: =EDATE(L5,1) -> 46533 | N5: =EDATE(M5,1) -> 46564 | O5: =EDATE(N5,1) -> 46594 | P5: =EDATE(O5,1) -> 46625 | ... T5: =EDATE(S5,1) -> 46747
B6: ='Actual Expenses'!B6 -> 11256 | C6: ='Actual Expenses'!C6 -> Marketing | D6: ='Actual Expenses'!D6 -> Paid Ads | E6: ='Actual Expenses'!E6 -> 22992 | F6: ='Actual Expenses'!F6 -> 24001 | G6: ='Actual Expenses'!G6 -> 26558 | H6: ='Actual Expenses'!H6 -> 25446 | I6: =CHOOSE('Income Statement'!$C$2,Forecast!I4,Forecast!I17,Forecast!I30) -> 18801.833 | J6: =CHOOSE('Income Statement'!$C$2,Forecast!J4,Forecast!J17,Forecast!J30) -> 18845.815 | K6: =CHOOSE('Income Statement'!$C$2,Forecast!K4,Forecast!K17,Forecast!K30) -> 19992.154 | L6: =CHOOSE('Income Statement'!$C$2,Forecast!L4,Forecast!L17,Forecast!L30) -> 19951.002 | M6: =CHOOSE('Income Statement'!$C$2,Forecast!M4,Forecast!M17,Forecast!M30) -> 21070.943 | N6: =CHOOSE('Income Statement'!$C$2,Forecast!N4,Forecast!N17,Forecast!N30) -> 21078.203 | O6: =CHOOSE('Income Statement'!$C$2,Forecast!O4,Forecast!O17,Forecast!O30) -> 22170.533 | P6: =CHOOSE('Income Statement'!$C$2,Forecast!P4,Forecast!P17,Forecast!P30) -> 22178.407 | ... T6: =CHOOSE('Income Statement'!$C$2,Forecast!T4,Forecast!T17,Forecast!T30) -> 24371.809
B7: ='Actual Expenses'!B7 -> 11257 | C7: ='Actual Expenses'!C7 -> Marketing | D7: ='Actual Expenses'!D7 -> Infuencers | E7: ='Actual Expenses'!E7 -> 53326 | F7: ='Actual Expenses'!F7 -> 54223 | G7: ='Actual Expenses'!G7 -> 51000 | H7: ='Actual Expenses'!H7 -> 50000 | I7: =CHOOSE('Income Statement'!$C$2,Forecast!I5,Forecast!I18,Forecast!I31) -> 34200.981 | J7: =CHOOSE('Income Statement'!$C$2,Forecast!J5,Forecast!J18,Forecast!J31) -> 33310.176 | K7: =CHOOSE('Income Statement'!$C$2,Forecast!K5,Forecast!K18,Forecast!K31) -> 32090.815 | L7: =CHOOSE('Income Statement'!$C$2,Forecast!L5,Forecast!L18,Forecast!L31) -> 31213.974 | M7: =CHOOSE('Income Statement'!$C$2,Forecast!M5,Forecast!M18,Forecast!M31) -> 30010.158 | N7: =CHOOSE('Income Statement'!$C$2,Forecast!N5,Forecast!N18,Forecast!N31) -> 29161.646 | O7: =CHOOSE('Income Statement'!$C$2,Forecast!O5,Forecast!O18,Forecast!O31) -> 27790.839 | P7: =CHOOSE('Income Statement'!$C$2,Forecast!P5,Forecast!P18,Forecast!P31) -> 26969.094 | ... T7: =CHOOSE('Income Statement'!$C$2,Forecast!T5,Forecast!T18,Forecast!T31) -> 22623.486
B8: ='Actual Expenses'!B8 -> 11259 | C8: ='Actual Expenses'!C8 -> Engineering | D8: ='Actual Expenses'!D8 -> Consulting | E8: ='Actual Expenses'!E8 -> 35888 | F8: ='Actual Expenses'!F8 -> 36880 | G8: ='Actual Expenses'!G8 -> 37995 | H8: ='Actual Expenses'!H8 -> 40000 | I8: =CHOOSE('Income Statement'!$C$2,Forecast!I6,Forecast!I19,Forecast!I32) -> 28828.78 | J8: =CHOOSE('Income Statement'!$C$2,Forecast!J6,Forecast!J19,Forecast!J32) -> 29829.57 | K8: =CHOOSE('Income Statement'!$C$2,Forecast!K6,Forecast!K19,Forecast!K32) -> 30825.318 | L8: =CHOOSE('Income Statement'!$C$2,Forecast!L6,Forecast!L19,Forecast!L32) -> 31789.738 | M8: =CHOOSE('Income Statement'!$C$2,Forecast!M6,Forecast!M19,Forecast!M32) -> 32770.197 | N8: =CHOOSE('Income Statement'!$C$2,Forecast!N6,Forecast!N19,Forecast!N32) -> 33750.718 | O8: =CHOOSE('Income Statement'!$C$2,Forecast!O6,Forecast!O19,Forecast!O32) -> 34731.303 | P8: =CHOOSE('Income Statement'!$C$2,Forecast!P6,Forecast!P19,Forecast!P32) -> 35711.936 | ... T8: =CHOOSE('Income Statement'!$C$2,Forecast!T6,Forecast!T19,Forecast!T32) -> 39634.614
B9: ='Actual Expenses'!B9 -> 11260 | C9: ='Actual Expenses'!C9 -> Engineering | D9: ='Actual Expenses'!D9 -> Travel | E9: ='Actual Expenses'!E9 -> 87942 | F9: ='Actual Expenses'!F9 -> 85224 | G9: ='Actual Expenses'!G9 -> 82469 | H9: ='Actual Expenses'!H9 -> 81005 | I9: =CHOOSE('Income Statement'!$C$2,Forecast!I7,Forecast!I20,Forecast!I33) -> 54899.524 | J9: =CHOOSE('Income Statement'!$C$2,Forecast!J7,Forecast!J20,Forecast!J33) -> 53324.63 | K9: =CHOOSE('Income Statement'!$C$2,Forecast!K7,Forecast!K20,Forecast!K33) -> 51738.726 | L9: =CHOOSE('Income Statement'!$C$2,Forecast!L7,Forecast!L20,Forecast!L33) -> 50128.337 | M9: =CHOOSE('Income Statement'!$C$2,Forecast!M7,Forecast!M20,Forecast!M33) -> 48532.325 | N9: =CHOOSE('Income Statement'!$C$2,Forecast!N7,Forecast!N20,Forecast!N33) -> 46935.402 | O9: =CHOOSE('Income Statement'!$C$2,Forecast!O7,Forecast!O20,Forecast!O33) -> 45337.88 | P9: =CHOOSE('Income Statement'!$C$2,Forecast!P7,Forecast!P20,Forecast!P33) -> 43736.51 | ... T9: =CHOOSE('Income Statement'!$C$2,Forecast!T7,Forecast!T20,Forecast!T33) -> 37341.371
B10: ='Actual Expenses'!B10 -> 11263 | C10: ='Actual Expenses'!C10 -> Support | D10: ='Actual Expenses'!D10 -> Software | E10: ='Actual Expenses'!E10 -> 92622 | F10: ='Actual Expenses'!F10 -> 90005 | G10: ='Actual Expenses'!G10 -> 87556 | H10: ='Actual Expenses'!H10 -> 84522 | I10: =CHOOSE('Income Statement'!$C$2,Forecast!I8,Forecast!I21,Forecast!I34) -> 57341.814 | J10: =CHOOSE('Income Statement'!$C$2,Forecast!J8,Forecast!J21,Forecast!J34) -> 55444.485 | K10: =CHOOSE('Income Statement'!$C$2,Forecast!K8,Forecast!K21,Forecast!K34) -> 53538.415 | L10: =CHOOSE('Income Statement'!$C$2,Forecast!L8,Forecast!L21,Forecast!L34) -> 51654.742 | M10: =CHOOSE('Income Statement'!$C$2,Forecast!M8,Forecast!M21,Forecast!M34) -> 49760.338 | N10: =CHOOSE('Income Statement'!$C$2,Forecast!N8,Forecast!N21,Forecast!N34) -> 47787.432 | O10: =CHOOSE('Income Statement'!$C$2,Forecast!O8,Forecast!O21,Forecast!O34) -> 45936.576 | P10: =CHOOSE('Income Statement'!$C$2,Forecast!P8,Forecast!P21,Forecast!P34) -> 44068.577 | ... T10: =CHOOSE('Income Statement'!$C$2,Forecast!T8,Forecast!T21,Forecast!T34) -> 36391.145
B11: ='Actual Expenses'!B11 -> 11264 | C11: ='Actual Expenses'!C11 -> Support | D11: ='Actual Expenses'!D11 -> Call Center | E11: ='Actual Expenses'!E11 -> 27416 | F11: ='Actual Expenses'!F11 -> 26554 | G11: ='Actual Expenses'!G11 -> 24330 | H11: ='Actual Expenses'!H11 -> 22338 | I11: =CHOOSE('Income Statement'!$C$2,Forecast!I9,Forecast!I22,Forecast!I35) -> 14549.274 | J11: =CHOOSE('Income Statement'!$C$2,Forecast!J9,Forecast!J22,Forecast!J35) -> 13276.457 | K11: =CHOOSE('Income Statement'!$C$2,Forecast!K9,Forecast!K22,Forecast!K35) -> 11997.136 | L11: =CHOOSE('Income Statement'!$C$2,Forecast!L9,Forecast!L22,Forecast!L35) -> 10778.931 | M11: =CHOOSE('Income Statement'!$C$2,Forecast!M9,Forecast!M22,Forecast!M35) -> 9537.5757 | N11: =CHOOSE('Income Statement'!$C$2,Forecast!N9,Forecast!N22,Forecast!N35) -> 8021.7835 | O11: =CHOOSE('Income Statement'!$C$2,Forecast!O9,Forecast!O22,Forecast!O35) -> 7164.9997 | P11: =CHOOSE('Income Statement'!$C$2,Forecast!P9,Forecast!P22,Forecast!P35) -> 5789.8934 | ... T11: =CHOOSE('Income Statement'!$C$2,Forecast!T9,Forecast!T22,Forecast!T35) -> 578.13463
B12: ='Actual Expenses'!B12 -> 11267 | C12: ='Actual Expenses'!C12 -> HR | D12: ='Actual Expenses'!D12 -> Recruiting Events | E12: ='Actual Expenses'!E12 -> 41696 | F12: ='Actual Expenses'!F12 -> 41696 | G12: ='Actual Expenses'!G12 -> 42558 | H12: ='Actual Expenses'!H12 -> 45448 | I12: =CHOOSE('Income Statement'!$C$2,Forecast!I10,Forecast!I23,Forecast!I36) -> 32379.863 | J12: =CHOOSE('Income Statement'!$C$2,Forecast!J10,Forecast!J23,Forecast!J36) -> 33393.247 | K12: =CHOOSE('Income Statement'!$C$2,Forecast!K10,Forecast!K23,Forecast!K36) -> 34405.12 | L12: =CHOOSE('Income Statement'!$C$2,Forecast!L10,Forecast!L23,Forecast!L36) -> 35316.63 | M12: =CHOOSE('Income Statement'!$C$2,Forecast!M10,Forecast!M23,Forecast!M36) -> 36277.04 | N12: =CHOOSE('Income Statement'!$C$2,Forecast!N10,Forecast!N23,Forecast!N36) -> 37237.62 | O12: =CHOOSE('Income Statement'!$C$2,Forecast!O10,Forecast!O23,Forecast!O36) -> 38198.382 | P12: =CHOOSE('Income Statement'!$C$2,Forecast!P10,Forecast!P23,Forecast!P36) -> 39159.274 | ... T12: =CHOOSE('Income Statement'!$C$2,Forecast!T10,Forecast!T23,Forecast!T36) -> 43003.214
B13: ='Actual Expenses'!B13 -> 11268 | C13: ='Actual Expenses'!C13 -> HR | D13: ='Actual Expenses'!D13 -> Meetups | E13: ='Actual Expenses'!E13 -> 60285 | F13: ='Actual Expenses'!F13 -> 61225 | G13: ='Actual Expenses'!G13 -> 68994 | H13: ='Actual Expenses'!H13 -> 72410 | I13: =CHOOSE('Income Statement'!$C$2,Forecast!I11,Forecast!I24,Forecast!I37) -> 53693.925 | J13: =CHOOSE('Income Statement'!$C$2,Forecast!J11,Forecast!J24,Forecast!J37) -> 56511.928 | K13: =CHOOSE('Income Statement'!$C$2,Forecast!K11,Forecast!K24,Forecast!K37) -> 60962.76 | L13: =CHOOSE('Income Statement'!$C$2,Forecast!L11,Forecast!L24,Forecast!L37) -> 63613.011 | M13: =CHOOSE('Income Statement'!$C$2,Forecast!M11,Forecast!M24,Forecast!M37) -> 67863.644 | N13: =CHOOSE('Income Statement'!$C$2,Forecast!N11,Forecast!N24,Forecast!N37) -> 70560.152 | O13: =CHOOSE('Income Statement'!$C$2,Forecast!O11,Forecast!O24,Forecast!O37) -> 74806.187 | P13: =CHOOSE('Income Statement'!$C$2,Forecast!P11,Forecast!P24,Forecast!P37) -> 77725.223 | ... T13: =CHOOSE('Income Statement'!$C$2,Forecast!T11,Forecast!T24,Forecast!T37) -> 91760.115
A39: x

Sheet Income Statement
B2: Operating Expenses Scenario | C2: 2
A4: x | B4: Income Statement Forecast
B5: in USD | C5: =Forecast!I3 -> 46413 | D5: =Forecast!J3 -> 46444 | E5: =Forecast!K3 -> 46472 | F5: =Forecast!L3 -> 46503 | G5: =Forecast!M3 -> 46533 | H5: =Forecast!N3 -> 46564 | I5: =Forecast!O3 -> 46594 | J5: =Forecast!P3 -> 46625 | ... N5: =Forecast!T3 -> 46747
B6: Revenue | C6: =C31 -> 441690.11 | D6: =D31 -> 434633.27 | E6: =E31 -> 434024.74 | F6: =F31 -> 426374.8 | G6: =G31 -> 425675.84 | H6: =H31 -> 418665.41 | I6: =I31 -> 559567.36 | J6: =J31 -> 550452.02 | ... N6: =N31 -> 526347.31
B7: COGS | C7: =C35 -> 88338.022 | D7: =D35 -> 86926.653 | E7: =E35 -> 86804.947 | F7: =F35 -> 85274.96 | G7: =G35 -> 85135.168 | H7: =H35 -> 83733.083 | I7: =I35 -> 111913.47 | J7: =J35 -> 110090.4 | ... N7: =N35 -> 105269.46
B8: Gross Profit | C8: =C6-C7 -> 353352.09 | D8: =D6-D7 -> 347706.61 | E8: =E6-E7 -> 347219.79 | F8: =F6-F7 -> 341099.84 | G8: =G6-G7 -> 340540.67 | H8: =H6-H7 -> 334932.33 | I8: =I6-I7 -> 447653.89 | J8: =J6-J7 -> 440361.61 | ... N8: =N6-N7 -> 421077.85
B10: Operating expenses:
B11: {=_xlfn.UNIQUE('Actual Expenses'!C6:C13)} -> Marketing | C11: =SUMIFS('Live Dynamic'!I$6:I$13,'Live Dynamic'!$C$6:$C$13,'Income Statement'!$B11) -> 53002.813 | D11: =SUMIFS('Live Dynamic'!J$6:J$13,'Live Dynamic'!$C$6:$C$13,'Income Statement'!$B11) -> 52155.992 | E11: =SUMIFS('Live Dynamic'!K$6:K$13,'Live Dynamic'!$C$6:$C$13,'Income Statement'!$B11) -> 52082.968 | F11: =SUMIFS('Live Dynamic'!L$6:L$13,'Live Dynamic'!$C$6:$C$13,'Income Statement'!$B11) -> 51164.976 | G11: =SUMIFS('Live Dynamic'!M$6:M$13,'Live Dynamic'!$C$6:$C$13,'Income Statement'!$B11) -> 51081.101 | H11: =SUMIFS('Live Dynamic'!N$6:N$13,'Live Dynamic'!$C$6:$C$13,'Income Statement'!$B11) -> 50239.85 | I11: =SUMIFS('Live Dynamic'!O$6:O$13,'Live Dynamic'!$C$6:$C$13,'Income Statement'!$B11) -> 49961.371 | J11: =SUMIFS('Live Dynamic'!P$6:P$13,'Live Dynamic'!$C$6:$C$13,'Income Statement'!$B11) -> 49147.501 | ... N11: =SUMIFS('Live Dynamic'!T$6:T$13,'Live Dynamic'!$C$6:$C$13,'Income Statement'!$B11) -> 46995.295
B12: Engineering | C12: =SUMIFS('Live Dynamic'!I$6:I$13,'Live Dynamic'!$C$6:$C$13,'Income Statement'!$B12) -> 83728.304 | D12: =SUMIFS('Live Dynamic'!J$6:J$13,'Live Dynamic'!$C$6:$C$13,'Income Statement'!$B12) -> 83154.201 | E12: =SUMIFS('Live Dynamic'!K$6:K$13,'Live Dynamic'!$C$6:$C$13,'Income Statement'!$B12) -> 82564.043 | F12: =SUMIFS('Live Dynamic'!L$6:L$13,'Live Dynamic'!$C$6:$C$13,'Income Statement'!$B12) -> 81918.076 | G12: =SUMIFS('Live Dynamic'!M$6:M$13,'Live Dynamic'!$C$6:$C$13,'Income Statement'!$B12) -> 81302.522 | H12: =SUMIFS('Live Dynamic'!N$6:N$13,'Live Dynamic'!$C$6:$C$13,'Income Statement'!$B12) -> 80686.12 | I12: =SUMIFS('Live Dynamic'!O$6:O$13,'Live Dynamic'!$C$6:$C$13,'Income Statement'!$B12) -> 80069.184 | J12: =SUMIFS('Live Dynamic'!P$6:P$13,'Live Dynamic'!$C$6:$C$13,'Income Statement'!$B12) -> 79448.446 | ... N12: =SUMIFS('Live Dynamic'!T$6:T$13,'Live Dynamic'!$C$6:$C$13,'Income Statement'!$B12) -> 76975.985
B13: Support | C13: =SUMIFS('Live Dynamic'!I$6:I$13,'Live Dynamic'!$C$6:$C$13,'Income Statement'!$B13) -> 71891.087 | D13: =SUMIFS('Live Dynamic'!J$6:J$13,'Live Dynamic'!$C$6:$C$13,'Income Statement'!$B13) -> 68720.943 | E13: =SUMIFS('Live Dynamic'!K$6:K$13,'Live Dynamic'!$C$6:$C$13,'Income Statement'!$B13) -> 65535.551 | F13: =SUMIFS('Live Dynamic'!L$6:L$13,'Live Dynamic'!$C$6:$C$13,'Income Statement'!$B13) -> 62433.673 | G13: =SUMIFS('Live Dynamic'!M$6:M$13,'Live Dynamic'!$C$6:$C$13,'Income Statement'!$B13) -> 59297.914 | H13: =SUMIFS('Live Dynamic'!N$6:N$13,'Live Dynamic'!$C$6:$C$13,'Income Statement'!$B13) -> 55809.216 | I13: =SUMIFS('Live Dynamic'!O$6:O$13,'Live Dynamic'!$C$6:$C$13,'Income Statement'!$B13) -> 53101.576 | J13: =SUMIFS('Live Dynamic'!P$6:P$13,'Live Dynamic'!$C$6:$C$13,'Income Statement'!$B13) -> 49858.47 | ... N13: =SUMIFS('Live Dynamic'!T$6:T$13,'Live Dynamic'!$C$6:$C$13,'Income Statement'!$B13) -> 36969.279
B14: HR | C14: =SUMIFS('Live Dynamic'!I$6:I$13,'Live Dynamic'!$C$6:$C$13,'Income Statement'!$B14) -> 86073.787 | D14: =SUMIFS('Live Dynamic'!J$6:J$13,'Live Dynamic'!$C$6:$C$13,'Income Statement'!$B14) -> 89905.175 | E14: =SUMIFS('Live Dynamic'!K$6:K$13,'Live Dynamic'!$C$6:$C$13,'Income Statement'!$B14) -> 95367.88 | F14: =SUMIFS('Live Dynamic'!L$6:L$13,'Live Dynamic'!$C$6:$C$13,'Income Statement'!$B14) -> 98929.641 | G14: =SUMIFS('Live Dynamic'!M$6:M$13,'Live Dynamic'!$C$6:$C$13,'Income Statement'!$B14) -> 104140.68 | H14: =SUMIFS('Live Dynamic'!N$6:N$13,'Live Dynamic'!$C$6:$C$13,'Income Statement'!$B14) -> 107797.77 | I14: =SUMIFS('Live Dynamic'!O$6:O$13,'Live Dynamic'!$C$6:$C$13,'Income Statement'!$B14) -> 113004.57 | J14: =SUMIFS('Live Dynamic'!P$6:P$13,'Live Dynamic'!$C$6:$C$13,'Income Statement'!$B14) -> 116884.5 | ... N14: =SUMIFS('Live Dynamic'!T$6:T$13,'Live Dynamic'!$C$6:$C$13,'Income Statement'!$B14) -> 134763.33
B15: Total operating expenses | C15: =SUM(C11:C14) -> 294695.99 | D15: =SUM(D11:D14) -> 293936.31 | E15: =SUM(E11:E14) -> 295550.44 | F15: =SUM(F11:F14) -> 294446.37 | G15: =SUM(G11:G14) -> 295822.22 | H15: =SUM(H11:H14) -> 294532.96 | I15: =SUM(I11:I14) -> 296136.7 | J15: =SUM(J11:J14) -> 295338.92 | ... N15: =SUM(N11:N14) -> 295703.89
B16: Operating income | C16: =C8-C15 -> 58656.097 | D16: =D8-D15 -> 53770.303 | E16: =E8-E15 -> 51669.347 | F16: =F8-F15 -> 46653.475 | G16: =G8-G15 -> 44718.453 | H16: =H8-H15 -> 40399.374 | I16: =I8-I15 -> 151517.19 | J16: =J8-J15 -> 145022.7 | ... N16: =N8-N15 -> 125373.96
B18: Other income / (expense), net | C18: =C38 -> 2208.4506 | D18: =D38 -> 2173.1663 | E18: =E38 -> 2170.1237 | F18: =F38 -> 2131.874 | G18: =G38 -> 2128.3792 | H18: =H38 -> 2093.3271 | I18: =I38 -> 2797.8368 | J18: =J38 -> 2752.2601 | ... N18: =N38 -> 2631.7365
B19: Pre-tax income | C19: =C16-C18 -> 56447.646 | D19: =D16-D18 -> 51597.137 | E19: =E16-E18 -> 49499.224 | F19: =F16-F18 -> 44521.601 | G19: =G16-G18 -> 42590.074 | H19: =H16-H18 -> 38306.046 | I19: =I16-I18 -> 148719.35 | J19: =J16-J18 -> 142270.44 | ... N19: =N16-N18 -> 122742.22
B21: Taxes | C21: =C19*$C$40 -> 14111.912 | D21: =D19*$C$40 -> 12899.284 | E21: =E19*$C$40 -> 12374.806 | F21: =F19*$C$40 -> 11130.4 | G21: =G19*$C$40 -> 10647.518 | H21: =H19*$C$40 -> 9576.5116 | I21: =I19*$C$40 -> 37179.838 | J21: =J19*$C$40 -> 35567.609 | ... N21: =N19*$C$40 -> 30685.555
B22: Net Income | C22: =C19-C21 -> 42335.735 | D22: =D19-D21 -> 38697.853 | E22: =E19-E21 -> 37124.418 | F22: =F19-F21 -> 33391.2 | G22: =G19-G21 -> 31942.555 | H22: =H19-H21 -> 28729.535 | I22: =I19-I21 -> 111539.51 | J22: =J19-J21 -> 106702.83 | ... N22: =N19-N21 -> 92056.665
A25: x
B26: Revenue
B27: Customer Acquisition Cost | C27: 30 | D27: 30 | E27: 30 | F27: 30 | G27: 30 | H27: 30 | I27: 25 | J27: 25 | K27: 25 | L27: 25 | M27: 25 | N27: 25
B28: Price | C28: 250 | D28: 250 | E28: 250 | F28: 250 | G28: 250 | H28: 250 | I28: 280 | J28: 280 | K28: 280 | L28: 280 | M28: 280 | N28: 280
B30: Units Sold | C30: =C11/C27 -> 1766.7604 | D30: =D11/D27 -> 1738.5331 | E30: =E11/E27 -> 1736.0989 | F30: =F11/F27 -> 1705.4992 | G30: =G11/G27 -> 1702.7034 | H30: =H11/H27 -> 1674.6617 | I30: =I11/I27 -> 1998.4549 | J30: =J11/J27 -> 1965.9001 | ... N30: =N11/N27 -> 1879.8118
B31: Revenue | C31: =C30*C28 -> 441690.11 | D31: =D30*D28 -> 434633.27 | E31: =E30*E28 -> 434024.74 | F31: =F30*F28 -> 426374.8 | G31: =G30*G28 -> 425675.84 | H31: =H30*H28 -> 418665.41 | I31: =I30*I28 -> 559567.36 | J31: =J30*J28 -> 550452.02 | ... N31: =N30*N28 -> 526347.31
B33: Other
B34: COGS % of Revenue | C34: 0.2 | D34: 0.2 | E34: 0.2 | F34: 0.2 | G34: 0.2 | H34: 0.2 | I34: 0.2 | J34: 0.2 | K34: 0.2 | L34: 0.2 | M34: 0.2 | N34: 0.2
B35: COGS | C35: =C31*C34 -> 88338.022 | D35: =D31*D34 -> 86926.653 | E35: =E31*E34 -> 86804.947 | F35: =F31*F34 -> 85274.96 | G35: =G31*G34 -> 85135.168 | H35: =H31*H34 -> 83733.083 | I35: =I31*I34 -> 111913.47 | J35: =J31*J34 -> 110090.4 | ... N35: =N31*N34 -> 105269.46
B37: Other income / (expense), net % of COGS | C37: 0.025 | D37: 0.025 | E37: 0.025 | F37: 0.025 | G37: 0.025 | H37: 0.025 | I37: 0.025 | J37: 0.025 | K37: 0.025 | L37: 0.025 | M37: 0.025 | N37: 0.025
B38: Other income / (expense), net | C38: =C37*C35 -> 2208.4506 | D38: =D37*D35 -> 2173.1663 | E38: =E37*E35 -> 2170.1237 | F38: =F37*F35 -> 2131.874 | G38: =G37*G35 -> 2128.3792 | H38: =H37*H35 -> 2093.3271 | I38: =I37*I35 -> 2797.8368 | J38: =J37*J35 -> 2752.2601 | ... N38: =N37*N35 -> 2631.7365
A40: x | B40: Tax Rate | C40: 0.25

Sheet __tracelight_scratchpad__
