Workbook

Sheet Cover
B3: PERSONAL FINANCE TRACKER
B4: Mohamed Magdy | FP&A Analyst
B5: Annual financial overview | Figures in USD
B7: EXECUTIVE SUMMARY
B8: TOTAL INCOME | D8: TOTAL EXPENSES | F8: TOTAL SAVINGS | H8: SAVINGS RATE
B9: =Dashboard!P10 -> 44691 | D9: =Dashboard!P20 -> 17865 | F9: =Dashboard!P23 -> 26826 | H9: =IF(Dashboard!P10=0,0,Dashboard!P23/Dashboard!P10) -> 0.60025508
B12: QUICK ACCESS
B13: Dashboard | E13: Inputs | H13: Latest activity
B14: Monthly insights | E14: Maintain data | H14: =MAX(Inputs!B5:B95) -> 44806
B17: CONTACT
B18: Email | C18: mohamedeones123@gmail.com | F18: LinkedIn | G18: linkedin.com/in/mohamed-magdy-finance
B19: Phone | C19: +20 101 301 9563 | F19: GitHub | G19: github.com/Mohamed-Magdy-Finance
B21: Clarity. | E21: Control. | H21: Insight.

Sheet Dashboard
B2: Personal Finance Tracker
B4: Figures in USD | C4: January | D4: February | E4: March | F4: April | G4: May | H4: June | I4: July | J4: August | K4: September | L4: October | M4: November | N4: December | P4: YTD Total
B5: Income:
B6: Base Salary | C6: =SUMIFS(Inputs!$F:$F,Inputs!$C:$C,Dashboard!C$4,Inputs!$D:$D,Dashboard!$B6) -> 3500 | D6: =SUMIFS(Inputs!$F:$F,Inputs!$C:$C,Dashboard!D$4,Inputs!$D:$D,Dashboard!$B6) -> 3500 | E6: =SUMIFS(Inputs!$F:$F,Inputs!$C:$C,Dashboard!E$4,Inputs!$D:$D,Dashboard!$B6) -> 3500 | F6: =SUMIFS(Inputs!$F:$F,Inputs!$C:$C,Dashboard!F$4,Inputs!$D:$D,Dashboard!$B6) -> 3500 | G6: =SUMIFS(Inputs!$F:$F,Inputs!$C:$C,Dashboard!G$4,Inputs!$D:$D,Dashboard!$B6) -> 3500 | H6: =SUMIFS(Inputs!$F:$F,Inputs!$C:$C,Dashboard!H$4,Inputs!$D:$D,Dashboard!$B6) -> 3500 | I6: =SUMIFS(Inputs!$F:$F,Inputs!$C:$C,Dashboard!I$4,Inputs!$D:$D,Dashboard!$B6) -> 3500 | J6: =SUMIFS(Inputs!$F:$F,Inputs!$C:$C,Dashboard!J$4,Inputs!$D:$D,Dashboard!$B6) -> 3500 | ... N6: =SUMIFS(Inputs!$F:$F,Inputs!$C:$C,Dashboard!N$4,Inputs!$D:$D,Dashboard!$B6) -> 0 | P6: =SUM(C6:N6) -> 28000
B7: Bonus | C7: =SUMIFS(Inputs!$F:$F,Inputs!$C:$C,Dashboard!C$4,Inputs!$D:$D,Dashboard!$B7) -> 850 | D7: =SUMIFS(Inputs!$F:$F,Inputs!$C:$C,Dashboard!D$4,Inputs!$D:$D,Dashboard!$B7) -> 1025 | E7: =SUMIFS(Inputs!$F:$F,Inputs!$C:$C,Dashboard!E$4,Inputs!$D:$D,Dashboard!$B7) -> 999 | F7: =SUMIFS(Inputs!$F:$F,Inputs!$C:$C,Dashboard!F$4,Inputs!$D:$D,Dashboard!$B7) -> 1243 | G7: =SUMIFS(Inputs!$F:$F,Inputs!$C:$C,Dashboard!G$4,Inputs!$D:$D,Dashboard!$B7) -> 1450 | H7: =SUMIFS(Inputs!$F:$F,Inputs!$C:$C,Dashboard!H$4,Inputs!$D:$D,Dashboard!$B7) -> 2232 | I7: =SUMIFS(Inputs!$F:$F,Inputs!$C:$C,Dashboard!I$4,Inputs!$D:$D,Dashboard!$B7) -> 2231 | J7: =SUMIFS(Inputs!$F:$F,Inputs!$C:$C,Dashboard!J$4,Inputs!$D:$D,Dashboard!$B7) -> 2300 | ... N7: =SUMIFS(Inputs!$F:$F,Inputs!$C:$C,Dashboard!N$4,Inputs!$D:$D,Dashboard!$B7) -> 0 | P7: =SUM(C7:N7) -> 12330
B8: Side Hustle | C8: =SUMIFS(Inputs!$F:$F,Inputs!$C:$C,Dashboard!C$4,Inputs!$D:$D,Dashboard!$B8) -> 199 | D8: =SUMIFS(Inputs!$F:$F,Inputs!$C:$C,Dashboard!D$4,Inputs!$D:$D,Dashboard!$B8) -> 228 | E8: =SUMIFS(Inputs!$F:$F,Inputs!$C:$C,Dashboard!E$4,Inputs!$D:$D,Dashboard!$B8) -> 59 | F8: =SUMIFS(Inputs!$F:$F,Inputs!$C:$C,Dashboard!F$4,Inputs!$D:$D,Dashboard!$B8) -> 258 | G8: =SUMIFS(Inputs!$F:$F,Inputs!$C:$C,Dashboard!G$4,Inputs!$D:$D,Dashboard!$B8) -> 1366 | H8: =SUMIFS(Inputs!$F:$F,Inputs!$C:$C,Dashboard!H$4,Inputs!$D:$D,Dashboard!$B8) -> 199 | I8: =SUMIFS(Inputs!$F:$F,Inputs!$C:$C,Dashboard!I$4,Inputs!$D:$D,Dashboard!$B8) -> 59 | J8: =SUMIFS(Inputs!$F:$F,Inputs!$C:$C,Dashboard!J$4,Inputs!$D:$D,Dashboard!$B8) -> 25 | ... N8: =SUMIFS(Inputs!$F:$F,Inputs!$C:$C,Dashboard!N$4,Inputs!$D:$D,Dashboard!$B8) -> 0 | P8: =SUM(C8:N8) -> 2393
B9: Investments | C9: =SUMIFS(Inputs!$F:$F,Inputs!$C:$C,Dashboard!C$4,Inputs!$D:$D,Dashboard!$B9) -> 0 | D9: =SUMIFS(Inputs!$F:$F,Inputs!$C:$C,Dashboard!D$4,Inputs!$D:$D,Dashboard!$B9) -> 195 | E9: =SUMIFS(Inputs!$F:$F,Inputs!$C:$C,Dashboard!E$4,Inputs!$D:$D,Dashboard!$B9) -> 299 | F9: =SUMIFS(Inputs!$F:$F,Inputs!$C:$C,Dashboard!F$4,Inputs!$D:$D,Dashboard!$B9) -> 359 | G9: =SUMIFS(Inputs!$F:$F,Inputs!$C:$C,Dashboard!G$4,Inputs!$D:$D,Dashboard!$B9) -> 0 | H9: =SUMIFS(Inputs!$F:$F,Inputs!$C:$C,Dashboard!H$4,Inputs!$D:$D,Dashboard!$B9) -> 250 | I9: =SUMIFS(Inputs!$F:$F,Inputs!$C:$C,Dashboard!I$4,Inputs!$D:$D,Dashboard!$B9) -> 215 | J9: =SUMIFS(Inputs!$F:$F,Inputs!$C:$C,Dashboard!J$4,Inputs!$D:$D,Dashboard!$B9) -> 350 | ... N9: =SUMIFS(Inputs!$F:$F,Inputs!$C:$C,Dashboard!N$4,Inputs!$D:$D,Dashboard!$B9) -> 0 | P9: =SUM(C9:N9) -> 1968
B10: Total Income | C10: =SUM(C6:C9) -> 4549 | D10: =SUM(D6:D9) -> 4948 | E10: =SUM(E6:E9) -> 4857 | F10: =SUM(F6:F9) -> 5360 | G10: =SUM(G6:G9) -> 6316 | H10: =SUM(H6:H9) -> 6181 | I10: =SUM(I6:I9) -> 6005 | J10: =SUM(J6:J9) -> 6175 | ... N10: =SUM(N6:N9) -> 0 | P10: =SUM(C10:N10) -> 44691
B11: MoM % growth | D11: =IF(D10=0,"",D10/C10-1) -> 0.087711585 | E11: =IF(E10=0,"",E10/D10-1) -> -0.018391269 | F11: =IF(F10=0,"",F10/E10-1) -> 0.10356187 | G11: =IF(G10=0,"",G10/F10-1) -> 0.17835821 | H11: =IF(H10=0,"",H10/G10-1) -> -0.021374288 | I11: =IF(I10=0,"",I10/H10-1) -> -0.028474357 | J11: =IF(J10=0,"",J10/I10-1) -> 0.028309742 | K11: =IF(K10=0,"",K10/J10-1) -> -0.951417 | ... N11: =IF(N10=0,"",N10/M10-1)
B13: Expenses:
B14: Rent | C14: =SUMIFS(Inputs!$F:$F,Inputs!$C:$C,Dashboard!C$4,Inputs!$D:$D,Dashboard!$B14) -> 1250 | D14: =SUMIFS(Inputs!$F:$F,Inputs!$C:$C,Dashboard!D$4,Inputs!$D:$D,Dashboard!$B14) -> 1250 | E14: =SUMIFS(Inputs!$F:$F,Inputs!$C:$C,Dashboard!E$4,Inputs!$D:$D,Dashboard!$B14) -> 1250 | F14: =SUMIFS(Inputs!$F:$F,Inputs!$C:$C,Dashboard!F$4,Inputs!$D:$D,Dashboard!$B14) -> 1250 | G14: =SUMIFS(Inputs!$F:$F,Inputs!$C:$C,Dashboard!G$4,Inputs!$D:$D,Dashboard!$B14) -> 1250 | H14: =SUMIFS(Inputs!$F:$F,Inputs!$C:$C,Dashboard!H$4,Inputs!$D:$D,Dashboard!$B14) -> 1250 | I14: =SUMIFS(Inputs!$F:$F,Inputs!$C:$C,Dashboard!I$4,Inputs!$D:$D,Dashboard!$B14) -> 1250 | J14: =SUMIFS(Inputs!$F:$F,Inputs!$C:$C,Dashboard!J$4,Inputs!$D:$D,Dashboard!$B14) -> 0 | ... N14: =SUMIFS(Inputs!$F:$F,Inputs!$C:$C,Dashboard!N$4,Inputs!$D:$D,Dashboard!$B14) -> 0 | P14: =SUM(C14:N14) -> 8750
B15: Utilities | C15: =SUMIFS(Inputs!$F:$F,Inputs!$C:$C,Dashboard!C$4,Inputs!$D:$D,Dashboard!$B15) -> 140 | D15: =SUMIFS(Inputs!$F:$F,Inputs!$C:$C,Dashboard!D$4,Inputs!$D:$D,Dashboard!$B15) -> 105 | E15: =SUMIFS(Inputs!$F:$F,Inputs!$C:$C,Dashboard!E$4,Inputs!$D:$D,Dashboard!$B15) -> 110 | F15: =SUMIFS(Inputs!$F:$F,Inputs!$C:$C,Dashboard!F$4,Inputs!$D:$D,Dashboard!$B15) -> 140 | G15: =SUMIFS(Inputs!$F:$F,Inputs!$C:$C,Dashboard!G$4,Inputs!$D:$D,Dashboard!$B15) -> 152 | H15: =SUMIFS(Inputs!$F:$F,Inputs!$C:$C,Dashboard!H$4,Inputs!$D:$D,Dashboard!$B15) -> 152 | I15: =SUMIFS(Inputs!$F:$F,Inputs!$C:$C,Dashboard!I$4,Inputs!$D:$D,Dashboard!$B15) -> 110 | J15: =SUMIFS(Inputs!$F:$F,Inputs!$C:$C,Dashboard!J$4,Inputs!$D:$D,Dashboard!$B15) -> 110 | ... N15: =SUMIFS(Inputs!$F:$F,Inputs!$C:$C,Dashboard!N$4,Inputs!$D:$D,Dashboard!$B15) -> 0 | P15: =SUM(C15:N15) -> 1019
B16: Transport | C16: =SUMIFS(Inputs!$F:$F,Inputs!$C:$C,Dashboard!C$4,Inputs!$D:$D,Dashboard!$B16) -> 52 | D16: =SUMIFS(Inputs!$F:$F,Inputs!$C:$C,Dashboard!D$4,Inputs!$D:$D,Dashboard!$B16) -> 52 | E16: =SUMIFS(Inputs!$F:$F,Inputs!$C:$C,Dashboard!E$4,Inputs!$D:$D,Dashboard!$B16) -> 52 | F16: =SUMIFS(Inputs!$F:$F,Inputs!$C:$C,Dashboard!F$4,Inputs!$D:$D,Dashboard!$B16) -> 52 | G16: =SUMIFS(Inputs!$F:$F,Inputs!$C:$C,Dashboard!G$4,Inputs!$D:$D,Dashboard!$B16) -> 52 | H16: =SUMIFS(Inputs!$F:$F,Inputs!$C:$C,Dashboard!H$4,Inputs!$D:$D,Dashboard!$B16) -> 52 | I16: =SUMIFS(Inputs!$F:$F,Inputs!$C:$C,Dashboard!I$4,Inputs!$D:$D,Dashboard!$B16) -> 45 | J16: =SUMIFS(Inputs!$F:$F,Inputs!$C:$C,Dashboard!J$4,Inputs!$D:$D,Dashboard!$B16) -> 52 | ... N16: =SUMIFS(Inputs!$F:$F,Inputs!$C:$C,Dashboard!N$4,Inputs!$D:$D,Dashboard!$B16) -> 0 | P16: =SUM(C16:N16) -> 409
B17: Groceries | C17: =SUMIFS(Inputs!$F:$F,Inputs!$C:$C,Dashboard!C$4,Inputs!$D:$D,Dashboard!$B17) -> 449 | D17: =SUMIFS(Inputs!$F:$F,Inputs!$C:$C,Dashboard!D$4,Inputs!$D:$D,Dashboard!$B17) -> 305 | E17: =SUMIFS(Inputs!$F:$F,Inputs!$C:$C,Dashboard!E$4,Inputs!$D:$D,Dashboard!$B17) -> 208 | F17: =SUMIFS(Inputs!$F:$F,Inputs!$C:$C,Dashboard!F$4,Inputs!$D:$D,Dashboard!$B17) -> 449 | G17: =SUMIFS(Inputs!$F:$F,Inputs!$C:$C,Dashboard!G$4,Inputs!$D:$D,Dashboard!$B17) -> 449 | H17: =SUMIFS(Inputs!$F:$F,Inputs!$C:$C,Dashboard!H$4,Inputs!$D:$D,Dashboard!$B17) -> 560 | I17: =SUMIFS(Inputs!$F:$F,Inputs!$C:$C,Dashboard!I$4,Inputs!$D:$D,Dashboard!$B17) -> 208 | J17: =SUMIFS(Inputs!$F:$F,Inputs!$C:$C,Dashboard!J$4,Inputs!$D:$D,Dashboard!$B17) -> 208 | ... N17: =SUMIFS(Inputs!$F:$F,Inputs!$C:$C,Dashboard!N$4,Inputs!$D:$D,Dashboard!$B17) -> 0 | P17: =SUM(C17:N17) -> 2836
B18: Leisure | C18: =SUMIFS(Inputs!$F:$F,Inputs!$C:$C,Dashboard!C$4,Inputs!$D:$D,Dashboard!$B18) -> 562 | D18: =SUMIFS(Inputs!$F:$F,Inputs!$C:$C,Dashboard!D$4,Inputs!$D:$D,Dashboard!$B18) -> 194 | E18: =SUMIFS(Inputs!$F:$F,Inputs!$C:$C,Dashboard!E$4,Inputs!$D:$D,Dashboard!$B18) -> 405 | F18: =SUMIFS(Inputs!$F:$F,Inputs!$C:$C,Dashboard!F$4,Inputs!$D:$D,Dashboard!$B18) -> 462 | G18: =SUMIFS(Inputs!$F:$F,Inputs!$C:$C,Dashboard!G$4,Inputs!$D:$D,Dashboard!$B18) -> 646 | H18: =SUMIFS(Inputs!$F:$F,Inputs!$C:$C,Dashboard!H$4,Inputs!$D:$D,Dashboard!$B18) -> 629 | I18: =SUMIFS(Inputs!$F:$F,Inputs!$C:$C,Dashboard!I$4,Inputs!$D:$D,Dashboard!$B18) -> 294 | J18: =SUMIFS(Inputs!$F:$F,Inputs!$C:$C,Dashboard!J$4,Inputs!$D:$D,Dashboard!$B18) -> 147 | ... N18: =SUMIFS(Inputs!$F:$F,Inputs!$C:$C,Dashboard!N$4,Inputs!$D:$D,Dashboard!$B18) -> 0 | P18: =SUM(C18:N18) -> 3339
B19: Other | C19: =SUMIFS(Inputs!$F:$F,Inputs!$C:$C,Dashboard!C$4,Inputs!$D:$D,Dashboard!$B19) -> 249 | D19: =SUMIFS(Inputs!$F:$F,Inputs!$C:$C,Dashboard!D$4,Inputs!$D:$D,Dashboard!$B19) -> 18 | E19: =SUMIFS(Inputs!$F:$F,Inputs!$C:$C,Dashboard!E$4,Inputs!$D:$D,Dashboard!$B19) -> 199 | F19: =SUMIFS(Inputs!$F:$F,Inputs!$C:$C,Dashboard!F$4,Inputs!$D:$D,Dashboard!$B19) -> 249 | G19: =SUMIFS(Inputs!$F:$F,Inputs!$C:$C,Dashboard!G$4,Inputs!$D:$D,Dashboard!$B19) -> 249 | H19: =SUMIFS(Inputs!$F:$F,Inputs!$C:$C,Dashboard!H$4,Inputs!$D:$D,Dashboard!$B19) -> 0 | I19: =SUMIFS(Inputs!$F:$F,Inputs!$C:$C,Dashboard!I$4,Inputs!$D:$D,Dashboard!$B19) -> 399 | J19: =SUMIFS(Inputs!$F:$F,Inputs!$C:$C,Dashboard!J$4,Inputs!$D:$D,Dashboard!$B19) -> 149 | ... N19: =SUMIFS(Inputs!$F:$F,Inputs!$C:$C,Dashboard!N$4,Inputs!$D:$D,Dashboard!$B19) -> 0 | P19: =SUM(C19:N19) -> 1512
B20: Total Expenses | C20: =SUM(C14:C19) -> 2702 | D20: =SUM(D14:D19) -> 1924 | E20: =SUM(E14:E19) -> 2224 | F20: =SUM(F14:F19) -> 2602 | G20: =SUM(G14:G19) -> 2798 | H20: =SUM(H14:H19) -> 2643 | I20: =SUM(I14:I19) -> 2306 | J20: =SUM(J14:J19) -> 666 | ... N20: =SUM(N14:N19) -> 0 | P20: =SUM(C20:N20) -> 17865
B21: MoM % growth | D21: =IF(D20=0,"",D20/C20-1) -> -0.28793486 | E21: =IF(E20=0,"",E20/D20-1) -> 0.15592516 | F21: =IF(F20=0,"",F20/E20-1) -> 0.16996403 | G21: =IF(G20=0,"",G20/F20-1) -> 0.075326672 | H21: =IF(H20=0,"",H20/G20-1) -> -0.055396712 | I21: =IF(I20=0,"",I20/H20-1) -> -0.12750662 | J21: =IF(J20=0,"",J20/I20-1) -> -0.7111882 | K21: =IF(K20=0,"",K20/J20-1) | ... N21: =IF(N20=0,"",N20/M20-1)
B23: Savings | C23: =C10-C20 -> 1847 | D23: =D10-D20 -> 3024 | E23: =E10-E20 -> 2633 | F23: =F10-F20 -> 2758 | G23: =G10-G20 -> 3518 | H23: =H10-H20 -> 3538 | I23: =I10-I20 -> 3699 | J23: =J10-J20 -> 5509 | ... N23: =N10-N20 -> 0 | P23: =SUM(C23:N23) -> 26826
B24: MoM % growth | D24: =IF(D23=0,"",D23/C23-1) -> 0.63724959 | E24: =IF(E23=0,"",E23/D23-1) -> -0.12929894 | F24: =IF(F23=0,"",F23/E23-1) -> 0.047474364 | G24: =IF(G23=0,"",G23/F23-1) -> 0.275562 | H24: =IF(H23=0,"",H23/G23-1) -> 0.0056850483 | I24: =IF(I23=0,"",I23/H23-1) -> 0.045505936 | J24: =IF(J23=0,"",J23/I23-1) -> 0.48932144 | K24: =IF(K23=0,"",K23/J23-1) -> -0.94554366 | ... N24: =IF(N23=0,"",N23/M23-1)
B27: Income Breakdown | G27: Expenses Breakdown

Sheet Inputs
B2: Actual Income & Expenses
B4: Date | C4: Month | D4: Category | E4: Description | F4: Amount | H4: Categories
B5: 44562 | C5: =TEXT(B5,"MMMM") -> January | D5: Rent | E5: Apartment split with friend | F5: 1250 | H5: Base Salary
B6: 44562 | C6: =TEXT(B6,"MMMM") -> January | D6: Utilities | E6: Higher month than usual | F6: 140 | H6: Bonus
B7: 44562 | C7: =TEXT(B7,"MMMM") -> January | D7: Transport | E7: Metro card | F7: 52 | H7: Side Hustle
B8: 44569 | C8: =TEXT(B8,"MMMM") -> January | D8: Groceries | E8: Walmart shopping | F8: 449 | H8: Investments
B9: 44572 | C9: =TEXT(B9,"MMMM") -> January | D9: Leisure | E9: Hotel in NYC | F9: 245 | H9: Rent
B10: 44573 | C10: =TEXT(B10,"MMMM") -> January | D10: Leisure | E10: Dinner with friends (invited my partner) | F10: 168 | H10: Utilities
B11: 44573 | C11: =TEXT(B11,"MMMM") -> January | D11: Leisure | E11: Drake concert | F11: 149 | H11: Transport
B12: 44575 | C12: =TEXT(B12,"MMMM") -> January | D12: Other | E12: Bought new clothes | F12: 249 | H12: Groceries
B13: 44592 | C13: =TEXT(B13,"MMMM") -> January | D13: Bonus | E13: Commissions from each sale | F13: 850 | H13: Leisure
B14: 44592 | C14: =TEXT(B14,"MMMM") -> January | D14: Base Salary | E14: 9-5 job | F14: 3500 | H14: Other
B15: 44592 | C15: =TEXT(B15,"MMMM") -> January | D15: Side Hustle | E15: Startup idea $ | F15: 199
B16: 44593 | C16: =TEXT(B16,"MMMM") -> February | D16: Rent | E16: Apartment split with friend | F16: 1250
B17: 44593 | C17: =TEXT(B17,"MMMM") -> February | D17: Utilities | E17: Average month | F17: 105
B18: 44593 | C18: =TEXT(B18,"MMMM") -> February | D18: Transport | E18: Metro card | F18: 52
B19: 44600 | C19: =TEXT(B19,"MMMM") -> February | D19: Groceries | E19: Walmart shopping | F19: 305
B20: 44603 | C20: =TEXT(B20,"MMMM") -> February | D20: Leisure | E20: Drinks out | F20: 28
B21: 44604 | C21: =TEXT(B21,"MMMM") -> February | D21: Leisure | E21: Date night | F21: 99
B22: 44604 | C22: =TEXT(B22,"MMMM") -> February | D22: Leisure | E22: Tennis x2 | F22: 67
B23: 44606 | C23: =TEXT(B23,"MMMM") -> February | D23: Other | E23: Snacks | F23: 18
B24: 44620 | C24: =TEXT(B24,"MMMM") -> February | D24: Bonus | E24: Commissions from each sale | F24: 1025
B25: 44620 | C25: =TEXT(B25,"MMMM") -> February | D25: Base Salary | E25: 9-5 job | F25: 3500
B26: 44620 | C26: =TEXT(B26,"MMMM") -> February | D26: Side Hustle | E26: Startup idea $ | F26: 228
... B57: 44693 | C57: =TEXT(B57,"MMMM") -> May | D57: Leisure | E57: Dinner with friends (invited my partner) | F57: 168
B58: 44693 | C58: =TEXT(B55,"MMMM") -> May | D58: Leisure | E58: NBA game | F58: 233
B59: 44695 | C59: =TEXT(B59,"MMMM") -> May | D59: Other | E59: Bought new clothes | F59: 249
B60: 44709 | C60: =TEXT(B60,"MMMM") -> May | D60: Bonus | E60: Commissions from each sale | F60: 1450
B61: 44709 | C61: =TEXT(B61,"MMMM") -> May | D61: Base Salary | E61: 9-5 job | F61: 3500
B62: 44709 | C62: =TEXT(B62,"MMMM") -> May | D62: Side Hustle | E62: Startup idea $ | F62: 366
B63: 44710 | C63: =TEXT(B63,"MMMM") -> May | D63: Side Hustle | E63: Lemonade | F63: 1000
B64: 44713 | C64: =TEXT(B64,"MMMM") -> June | D64: Rent | E64: Apartment split with friend | F64: 1250
B65: 44713 | C65: =TEXT(B65,"MMMM") -> June | D65: Utilities | E65: Higher month than usual | F65: 152
B66: 44713 | C66: =TEXT(B66,"MMMM") -> June | D66: Transport | E66: Metro card | F66: 52
B67: 44720 | C67: =TEXT(B67,"MMMM") -> June | D67: Groceries | E67: Walmart shopping | F67: 560
B68: 44723 | C68: =TEXT(B68,"MMMM") -> June | D68: Leisure | E68: Hotel in Dallas | F68: 280
B69: 44724 | C69: =TEXT(B69,"MMMM") -> June | D69: Leisure | E69: Dinner with friends (invited my partner) | F69: 250
B70: 44724 | C70: =TEXT(B70,"MMMM") -> June | D70: Leisure | E70: Music concert | F70: 99
... B95: 44806 | C95: =TEXT(B95,"MMMM") -> September | D95: Investments | E95: Stock Dividends | F95: 300

Sheet __tracelight_scratchpad__
